[
  {
    "date": "2025-07-19T13:00:00+00:00",
    "season": 2025,
    "home": "Manchester United",
    "away": "Leeds",
    "home_id": 33,
    "away_id": 63,
    "home_score": 0,
    "away_score": 0,
    "points": 1,
    "is_home": true,
    "corners_for": 0,
    "corners_ag": 0
  },
  {
    "date": "2025-08-17T15:30:00+00:00",
    "season": 2025,
    "home": "Manchester United",
    "away": "Arsenal",
    "home_id": 33,
    "away_id": 42,
    "home_score": 0,
    "away_score": 1,
    "points": 0,
    "is_home": true,
    "corners_for": 0,
    "corners_ag": 0
  },
  {
    "date": "2025-08-24T15:30:00+00:00",
    "season": 2025,
    "home": "Fulham",
    "away": "Manchester United",
    "home_id": 36,
    "away_id": 33,
    "home_score": 1,
    "away_score": 1,
    "points": 1,
    "is_home": false,
    "corners_for": 0,
    "corners_ag": 0
  },
  {
    "date": "2025-08-30T14:00:00+00:00",
    "season": 2025,
    "home": "Manchester United",
    "away": "Burnley",
    "home_id": 33,
    "away_id": 44,
    "home_score": 3,
    "away_score": 2,
    "points": 3,
    "is_home": true,
    "corners_for": 0,
    "corners_ag": 0
  },
  {
    "date": "2025-09-14T15:30:00+00:00",
    "season": 2025,
    "home": "Manchester City",
    "away": "Manchester United",
    "home_id": 50,
    "away_id": 33,
    "home_score": 3,
    "away_score": 0,
    "points": 0,
    "is_home": false,
    "corners_for": 0,
    "corners_ag": 0
  },
  {
    "date": "2025-09-20T16:30:00+00:00",
    "season": 2025,
    "home": "Manchester United",
    "away": "Chelsea",
    "home_id": 33,
    "away_id": 49,
    "home_score": 2,
    "away_score": 1,
    "points": 3,
    "is_home": true,
    "corners_for": 0,
    "corners_ag": 0
  },
  {
    "date": "2025-09-27T11:30:00+00:00",
    "season": 2025,
    "home": "Brentford",
    "away": "Manchester United",
    "home_id": 55,
    "away_id": 33,
    "home_score": 3,
    "away_score": 1,
    "points": 0,
    "is_home": false,
    "corners_for": 0,
    "corners_ag": 0
  },
  {
    "date": "2025-10-04T14:00:00+00:00",
    "season": 2025,
    "home": "Manchester United",
    "away": "Sunderland",
    "home_id": 33,
    "away_id": 746,
    "home_score": 2,
    "away_score": 0,
    "points": 3,
    "is_home": true,
    "corners_for": 0,
    "corners_ag": 0
  },
  {
    "date": "2025-10-19T15:30:00+00:00",
    "season": 2025,
    "home": "Liverpool",
    "away": "Manchester United",
    "home_id": 40,
    "away_id": 33,
    "home_score": 1,
    "away_score": 2,
    "points": 3,
    "is_home": false,
    "corners_for": 0,
    "corners_ag": 0
  },
  {
    "date": "2025-10-25T16:30:00+00:00",
    "season": 2025,
    "home": "Manchester United",
    "away": "Brighton",
    "home_id": 33,
    "away_id": 51,
    "home_score": 4,
    "away_score": 2,
    "points": 3,
    "is_home": true,
    "corners_for": 0,
    "corners_ag": 0
  },
  {
    "date": "2025-11-01T15:00:00+00:00",
    "season": 2025,
    "home": "Nottingham Forest",
    "away": "Manchester United",
    "home_id": 65,
    "away_id": 33,
    "home_score": 2,
    "away_score": 2,
    "points": 1,
    "is_home": false,
    "corners_for": 0,
    "corners_ag": 0
  },
  {
    "date": "2025-11-08T12:30:00+00:00",
    "season": 2025,
    "home": "Tottenham",
    "away": "Manchester United",
    "home_id": 47,
    "away_id": 33,
    "home_score": 2,
    "away_score": 2,
    "points": 1,
    "is_home": false,
    "corners_for": 0,
    "corners_ag": 0
  },
  {
    "date": "2025-11-24T20:00:00+00:00",
    "season": 2025,
    "home": "Manchester United",
    "away": "Everton",
    "home_id": 33,
    "away_id": 45,
    "home_score": 0,
    "away_score": 1,
    "points": 0,
    "is_home": true,
    "corners_for": 0,
    "corners_ag": 0
  },
  {
    "date": "2025-11-30T12:00:00+00:00",
    "season": 2025,
    "home": "Crystal Palace",
    "away": "Manchester United",
    "home_id": 52,
    "away_id": 33,
    "home_score": 1,
    "away_score": 2,
    "points": 3,
    "is_home": false,
    "corners_for": 0,
    "corners_ag": 0
  },
  {
    "date": "2025-12-04T20:00:00+00:00",
    "season": 2025,
    "home": "Manchester United",
    "away": "West Ham",
    "home_id": 33,
    "away_id": 48,
    "home_score": 1,
    "away_score": 1,
    "points": 1,
    "is_home": true,
    "corners_for": 0,
    "corners_ag": 0
  },
  {
    "date": "2025-12-08T20:00:00+00:00",
    "season": 2025,
    "home": "Wolves",
    "away": "Manchester United",
    "home_id": 39,
    "away_id": 33,
    "home_score": 1,
    "away_score": 4,
    "points": 3,
    "is_home": false,
    "corners_for": 0,
    "corners_ag": 0
  },
  {
    "date": "2025-12-15T20:00:00+00:00",
    "season": 2025,
    "home": "Manchester United",
    "away": "Bournemouth",
    "home_id": 33,
    "away_id": 35,
    "home_score": 4,
    "away_score": 4,
    "points": 1,
    "is_home": true,
    "corners_for": 0,
    "corners_ag": 0
  },
  {
    "date": "2025-12-21T16:30:00+00:00",
    "season": 2025,
    "home": "Aston Villa",
    "away": "Manchester United",
    "home_id": 66,
    "away_id": 33,
    "home_score": 2,
    "away_score": 1,
    "points": 0,
    "is_home": false,
    "corners_for": 0,
    "corners_ag": 0
  },
  {
    "date": "2025-12-26T20:00:00+00:00",
    "season": 2025,
    "home": "Manchester United",
    "away": "Newcastle",
    "home_id": 33,
    "away_id": 34,
    "home_score": 1,
    "away_score": 0,
    "points": 3,
    "is_home": true,
    "corners_for": 0,
    "corners_ag": 0
  },
  {
    "date": "2025-12-30T20:15:00+00:00",
    "season": 2025,
    "home": "Manchester United",
    "away": "Wolves",
    "home_id": 33,
    "away_id": 39,
    "home_score": 1,
    "away_score": 1,
    "points": 1,
    "is_home": true,
    "corners_for": 0,
    "corners_ag": 0
  },
  {
    "date": "2026-01-04T12:30:00+00:00",
    "season": 2025,
    "home": "Leeds",
    "away": "Manchester United",
    "home_id": 63,
    "away_id": 33,
    "home_score": 1,
    "away_score": 1,
    "points": 1,
    "is_home": false,
    "corners_for": 0,
    "corners_ag": 0
  },
  {
    "date": "2026-01-07T20:15:00+00:00",
    "season": 2025,
    "home": "Burnley",
    "away": "Manchester United",
    "home_id": 44,
    "away_id": 33,
    "home_score": 2,
    "away_score": 2,
    "points": 1,
    "is_home": false,
    "corners_for": 0,
    "corners_ag": 0
  },
  {
    "date": "2026-01-17T12:30:00+00:00",
    "season": 2025,
    "home": "Manchester United",
    "away": "Manchester City",
    "home_id": 33,
    "away_id": 50,
    "home_score": 2,
    "away_score": 0,
    "points": 3,
    "is_home": true,
    "corners_for": 0,
    "corners_ag": 0
  },
  {
    "date": "2026-01-25T16:30:00+00:00",
    "season": 2025,
    "home": "Arsenal",
    "away": "Manchester United",
    "home_id": 42,
    "away_id": 33,
    "home_score": 2,
    "away_score": 3,
    "points": 3,
    "is_home": false,
    "corners_for": 0,
    "corners_ag": 0
  },
  {
    "date": "2026-02-01T14:00:00+00:00",
    "season": 2025,
    "home": "Manchester United",
    "away": "Fulham",
    "home_id": 33,
    "away_id": 36,
    "home_score": 3,
    "away_score": 2,
    "points": 3,
    "is_home": true,
    "corners_for": 0,
    "corners_ag": 0
  },
  {
    "date": "2026-02-07T12:30:00+00:00",
    "season": 2025,
    "home": "Manchester United",
    "away": "Tottenham",
    "home_id": 33,
    "away_id": 47,
    "home_score": 2,
    "away_score": 0,
    "points": 3,
    "is_home": true,
    "corners_for": 0,
    "corners_ag": 0
  },
  {
    "date": "2026-02-10T20:15:00+00:00",
    "season": 2025,
    "home": "West Ham",
    "away": "Manchester United",
    "home_id": 48,
    "away_id": 33,
    "home_score": 1,
    "away_score": 1,
    "points": 1,
    "is_home": false,
    "corners_for": 0,
    "corners_ag": 0
  },
  {
    "date": "2026-02-23T20:00:00+00:00",
    "season": 2025,
    "home": "Everton",
    "away": "Manchester United",
    "home_id": 45,
    "away_id": 33,
    "home_score": 0,
    "away_score": 1,
    "points": 3,
    "is_home": false,
    "corners_for": 0,
    "corners_ag": 0
  },
  {
    "date": "2026-03-01T14:00:00+00:00",
    "season": 2025,
    "home": "Manchester United",
    "away": "Crystal Palace",
    "home_id": 33,
    "away_id": 52,
    "home_score": 2,
    "away_score": 1,
    "points": 3,
    "is_home": true,
    "corners_for": 0,
    "corners_ag": 0
  },
  {
    "date": "2026-03-04T20:15:00+00:00",
    "season": 2025,
    "home": "Newcastle",
    "away": "Manchester United",
    "home_id": 34,
    "away_id": 33,
    "home_score": 2,
    "away_score": 1,
    "points": 0,
    "is_home": false,
    "corners_for": 0,
    "corners_ag": 0
  },
  {
    "date": "2026-03-15T14:00:00+00:00",
    "season": 2025,
    "home": "Manchester United",
    "away": "Aston Villa",
    "home_id": 33,
    "away_id": 66,
    "home_score": 3,
    "away_score": 1,
    "points": 3,
    "is_home": true,
    "corners_for": 0,
    "corners_ag": 0
  },
  {
    "date": "2026-03-20T20:00:00+00:00",
    "season": 2025,
    "home": "Bournemouth",
    "away": "Manchester United",
    "home_id": 35,
    "away_id": 33,
    "home_score": 2,
    "away_score": 2,
    "points": 1,
    "is_home": false,
    "corners_for": 0,
    "corners_ag": 0
  },
  {
    "date": "2026-01-11T16:30:00+00:00",
    "season": 2025,
    "home": "Manchester United",
    "away": "Brighton",
    "home_id": 33,
    "away_id": 51,
    "home_score": 1,
    "away_score": 2,
    "points": 0,
    "is_home": true,
    "corners_for": 0,
    "corners_ag": 0
  }
]