[
  {
    "date": "2021-08-14T13:30:00+00:00",
    "season": 2021,
    "home": "VfL Wolfsburg",
    "away": "Vfl Bochum",
    "home_id": 161,
    "away_id": 176,
    "home_score": 1,
    "away_score": 0,
    "points": 3,
    "is_home": true,
    "corners_for": 0,
    "corners_ag": 0
  },
  {
    "date": "2021-08-21T13:30:00+00:00",
    "season": 2021,
    "home": "Hertha Berlin",
    "away": "VfL Wolfsburg",
    "home_id": 159,
    "away_id": 161,
    "home_score": 1,
    "away_score": 2,
    "points": 3,
    "is_home": false,
    "corners_for": 0,
    "corners_ag": 0
  },
  {
    "date": "2021-08-29T15:30:00+00:00",
    "season": 2021,
    "home": "VfL Wolfsburg",
    "away": "RB Leipzig",
    "home_id": 161,
    "away_id": 173,
    "home_score": 1,
    "away_score": 0,
    "points": 3,
    "is_home": true,
    "corners_for": 0,
    "corners_ag": 0
  },
  {
    "date": "2021-09-11T13:30:00+00:00",
    "season": 2021,
    "home": "SpVgg Greuther Furth",
    "away": "VfL Wolfsburg",
    "home_id": 178,
    "away_id": 161,
    "home_score": 0,
    "away_score": 2,
    "points": 3,
    "is_home": false,
    "corners_for": 0,
    "corners_ag": 0
  },
  {
    "date": "2021-09-19T17:30:00+00:00",
    "season": 2021,
    "home": "VfL Wolfsburg",
    "away": "Eintracht Frankfurt",
    "home_id": 161,
    "away_id": 169,
    "home_score": 1,
    "away_score": 1,
    "points": 1,
    "is_home": true,
    "corners_for": 0,
    "corners_ag": 0
  },
  {
    "date": "2021-09-25T13:30:00+00:00",
    "season": 2021,
    "home": "1899 Hoffenheim",
    "away": "VfL Wolfsburg",
    "home_id": 167,
    "away_id": 161,
    "home_score": 3,
    "away_score": 1,
    "points": 0,
    "is_home": false,
    "corners_for": 0,
    "corners_ag": 0
  },
  {
    "date": "2021-10-02T13:30:00+00:00",
    "season": 2021,
    "home": "VfL Wolfsburg",
    "away": "Borussia Monchengladbach",
    "home_id": 161,
    "away_id": 163,
    "home_score": 1,
    "away_score": 3,
    "points": 0,
    "is_home": true,
    "corners_for": 0,
    "corners_ag": 0
  },
  {
    "date": "2021-10-16T13:30:00+00:00",
    "season": 2021,
    "home": "Union Berlin",
    "away": "VfL Wolfsburg",
    "home_id": 182,
    "away_id": 161,
    "home_score": 2,
    "away_score": 0,
    "points": 0,
    "is_home": false,
    "corners_for": 0,
    "corners_ag": 0
  },
  {
    "date": "2021-10-23T13:30:00+00:00",
    "season": 2021,
    "home": "VfL Wolfsburg",
    "away": "SC Freiburg",
    "home_id": 161,
    "away_id": 160,
    "home_score": 0,
    "away_score": 2,
    "points": 0,
    "is_home": true,
    "corners_for": 0,
    "corners_ag": 0
  },
  {
    "date": "2021-10-30T13:30:00+00:00",
    "season": 2021,
    "home": "Bayer Leverkusen",
    "away": "VfL Wolfsburg",
    "home_id": 168,
    "away_id": 161,
    "home_score": 0,
    "away_score": 2,
    "points": 3,
    "is_home": false,
    "corners_for": 0,
    "corners_ag": 0
  },
  {
    "date": "2021-11-06T14:30:00+00:00",
    "season": 2021,
    "home": "VfL Wolfsburg",
    "away": "FC Augsburg",
    "home_id": 161,
    "away_id": 170,
    "home_score": 1,
    "away_score": 0,
    "points": 3,
    "is_home": true,
    "corners_for": 0,
    "corners_ag": 0
  },
  {
    "date": "2021-11-20T14:30:00+00:00",
    "season": 2021,
    "home": "Arminia Bielefeld",
    "away": "VfL Wolfsburg",
    "home_id": 188,
    "away_id": 161,
    "home_score": 2,
    "away_score": 2,
    "points": 1,
    "is_home": false,
    "corners_for": 0,
    "corners_ag": 0
  },
  {
    "date": "2021-11-27T14:30:00+00:00",
    "season": 2021,
    "home": "VfL Wolfsburg",
    "away": "Borussia Dortmund",
    "home_id": 161,
    "away_id": 165,
    "home_score": 1,
    "away_score": 3,
    "points": 0,
    "is_home": true,
    "corners_for": 0,
    "corners_ag": 0
  },
  {
    "date": "2021-12-04T14:30:00+00:00",
    "season": 2021,
    "home": "FSV Mainz 05",
    "away": "VfL Wolfsburg",
    "home_id": 164,
    "away_id": 161,
    "home_score": 3,
    "away_score": 0,
    "points": 0,
    "is_home": false,
    "corners_for": 0,
    "corners_ag": 0
  },
  {
    "date": "2021-12-11T17:30:00+00:00",
    "season": 2021,
    "home": "VfL Wolfsburg",
    "away": "VfB Stuttgart",
    "home_id": 161,
    "away_id": 172,
    "home_score": 0,
    "away_score": 2,
    "points": 0,
    "is_home": true,
    "corners_for": 0,
    "corners_ag": 0
  },
  {
    "date": "2021-12-14T19:30:00+00:00",
    "season": 2021,
    "home": "VfL Wolfsburg",
    "away": "1. FC Köln",
    "home_id": 161,
    "away_id": 192,
    "home_score": 2,
    "away_score": 3,
    "points": 0,
    "is_home": true,
    "corners_for": 0,
    "corners_ag": 0
  },
  {
    "date": "2021-12-17T19:30:00+00:00",
    "season": 2021,
    "home": "Bayern Munich",
    "away": "VfL Wolfsburg",
    "home_id": 157,
    "away_id": 161,
    "home_score": 4,
    "away_score": 0,
    "points": 0,
    "is_home": false,
    "corners_for": 0,
    "corners_ag": 0
  },
  {
    "date": "2022-01-09T16:30:00+00:00",
    "season": 2021,
    "home": "Vfl Bochum",
    "away": "VfL Wolfsburg",
    "home_id": 176,
    "away_id": 161,
    "home_score": 1,
    "away_score": 0,
    "points": 0,
    "is_home": false,
    "corners_for": 0,
    "corners_ag": 0
  },
  {
    "date": "2022-01-15T14:30:00+00:00",
    "season": 2021,
    "home": "VfL Wolfsburg",
    "away": "Hertha Berlin",
    "home_id": 161,
    "away_id": 159,
    "home_score": 0,
    "away_score": 0,
    "points": 1,
    "is_home": true,
    "corners_for": 0,
    "corners_ag": 0
  },
  {
    "date": "2022-01-23T14:30:00+00:00",
    "season": 2021,
    "home": "RB Leipzig",
    "away": "VfL Wolfsburg",
    "home_id": 173,
    "away_id": 161,
    "home_score": 2,
    "away_score": 0,
    "points": 0,
    "is_home": false,
    "corners_for": 0,
    "corners_ag": 0
  },
  {
    "date": "2022-02-06T16:30:00+00:00",
    "season": 2021,
    "home": "VfL Wolfsburg",
    "away": "SpVgg Greuther Furth",
    "home_id": 161,
    "away_id": 178,
    "home_score": 4,
    "away_score": 1,
    "points": 3,
    "is_home": true,
    "corners_for": 0,
    "corners_ag": 0
  },
  {
    "date": "2022-02-12T14:30:00+00:00",
    "season": 2021,
    "home": "Eintracht Frankfurt",
    "away": "VfL Wolfsburg",
    "home_id": 169,
    "away_id": 161,
    "home_score": 0,
    "away_score": 2,
    "points": 3,
    "is_home": false,
    "corners_for": 0,
    "corners_ag": 0
  },
  {
    "date": "2022-02-19T14:30:00+00:00",
    "season": 2021,
    "home": "VfL Wolfsburg",
    "away": "1899 Hoffenheim",
    "home_id": 161,
    "away_id": 167,
    "home_score": 1,
    "away_score": 2,
    "points": 0,
    "is_home": true,
    "corners_for": 0,
    "corners_ag": 0
  },
  {
    "date": "2022-02-26T14:30:00+00:00",
    "season": 2021,
    "home": "Borussia Monchengladbach",
    "away": "VfL Wolfsburg",
    "home_id": 163,
    "away_id": 161,
    "home_score": 2,
    "away_score": 2,
    "points": 1,
    "is_home": false,
    "corners_for": 0,
    "corners_ag": 0
  },
  {
    "date": "2022-03-05T14:30:00+00:00",
    "season": 2021,
    "home": "VfL Wolfsburg",
    "away": "Union Berlin",
    "home_id": 161,
    "away_id": 182,
    "home_score": 1,
    "away_score": 0,
    "points": 3,
    "is_home": true,
    "corners_for": 0,
    "corners_ag": 0
  },
  {
    "date": "2022-03-12T14:30:00+00:00",
    "season": 2021,
    "home": "SC Freiburg",
    "away": "VfL Wolfsburg",
    "home_id": 160,
    "away_id": 161,
    "home_score": 3,
    "away_score": 2,
    "points": 0,
    "is_home": false,
    "corners_for": 0,
    "corners_ag": 0
  },
  {
    "date": "2022-03-20T16:30:00+00:00",
    "season": 2021,
    "home": "VfL Wolfsburg",
    "away": "Bayer Leverkusen",
    "home_id": 161,
    "away_id": 168,
    "home_score": 0,
    "away_score": 2,
    "points": 0,
    "is_home": true,
    "corners_for": 0,
    "corners_ag": 0
  },
  {
    "date": "2022-04-03T13:30:00+00:00",
    "season": 2021,
    "home": "FC Augsburg",
    "away": "VfL Wolfsburg",
    "home_id": 170,
    "away_id": 161,
    "home_score": 3,
    "away_score": 0,
    "points": 0,
    "is_home": false,
    "corners_for": 0,
    "corners_ag": 0
  },
  {
    "date": "2022-04-09T13:30:00+00:00",
    "season": 2021,
    "home": "VfL Wolfsburg",
    "away": "Arminia Bielefeld",
    "home_id": 161,
    "away_id": 188,
    "home_score": 4,
    "away_score": 0,
    "points": 3,
    "is_home": true,
    "corners_for": 0,
    "corners_ag": 0
  },
  {
    "date": "2022-04-16T13:30:00+00:00",
    "season": 2021,
    "home": "Borussia Dortmund",
    "away": "VfL Wolfsburg",
    "home_id": 165,
    "away_id": 161,
    "home_score": 6,
    "away_score": 1,
    "points": 0,
    "is_home": false,
    "corners_for": 0,
    "corners_ag": 0
  },
  {
    "date": "2022-04-22T18:30:00+00:00",
    "season": 2021,
    "home": "VfL Wolfsburg",
    "away": "FSV Mainz 05",
    "home_id": 161,
    "away_id": 164,
    "home_score": 5,
    "away_score": 0,
    "points": 3,
    "is_home": true,
    "corners_for": 0,
    "corners_ag": 0
  },
  {
    "date": "2022-04-30T13:30:00+00:00",
    "season": 2021,
    "home": "VfB Stuttgart",
    "away": "VfL Wolfsburg",
    "home_id": 172,
    "away_id": 161,
    "home_score": 1,
    "away_score": 1,
    "points": 1,
    "is_home": false,
    "corners_for": 0,
    "corners_ag": 0
  },
  {
    "date": "2022-05-07T13:30:00+00:00",
    "season": 2021,
    "home": "1. FC Köln",
    "away": "VfL Wolfsburg",
    "home_id": 192,
    "away_id": 161,
    "home_score": 0,
    "away_score": 1,
    "points": 3,
    "is_home": false,
    "corners_for": 0,
    "corners_ag": 0
  },
  {
    "date": "2022-05-14T13:30:00+00:00",
    "season": 2021,
    "home": "VfL Wolfsburg",
    "away": "Bayern Munich",
    "home_id": 161,
    "away_id": 157,
    "home_score": 2,
    "away_score": 2,
    "points": 1,
    "is_home": true,
    "corners_for": 0,
    "corners_ag": 0
  },
  {
    "date": "2021-07-06T00:00:00+00:00",
    "season": 2021,
    "home": "VfL Wolfsburg",
    "away": "Erzgebirge AUE",
    "home_id": 161,
    "away_id": 190,
    "home_score": 2,
    "away_score": 1,
    "points": 3,
    "is_home": true,
    "corners_for": 0,
    "corners_ag": 0
  },
  {
    "date": "2021-07-10T00:00:00+00:00",
    "season": 2021,
    "home": "VfL Wolfsburg",
    "away": "Hansa Rostock",
    "home_id": 161,
    "away_id": 1321,
    "home_score": 0,
    "away_score": 3,
    "points": 0,
    "is_home": true,
    "corners_for": 0,
    "corners_ag": 0
  },
  {
    "date": "2021-07-14T14:00:00+00:00",
    "season": 2021,
    "home": "VfL Wolfsburg",
    "away": "Holstein Kiel",
    "home_id": 161,
    "away_id": 191,
    "home_score": 0,
    "away_score": 1,
    "points": 0,
    "is_home": true,
    "corners_for": 0,
    "corners_ag": 0
  },
  {
    "date": "2021-07-17T19:05:00+00:00",
    "season": 2021,
    "home": "Lyon",
    "away": "VfL Wolfsburg",
    "home_id": 80,
    "away_id": 161,
    "home_score": 4,
    "away_score": 1,
    "points": 0,
    "is_home": false,
    "corners_for": 0,
    "corners_ag": 0
  },
  {
    "date": "2021-07-24T14:00:00+00:00",
    "season": 2021,
    "home": "VfL Wolfsburg",
    "away": "Monaco",
    "home_id": 161,
    "away_id": 91,
    "home_score": 1,
    "away_score": 2,
    "points": 0,
    "is_home": true,
    "corners_for": 0,
    "corners_ag": 0
  },
  {
    "date": "2021-07-31T00:00:00+00:00",
    "season": 2021,
    "home": "VfL Wolfsburg",
    "away": "Atletico Madrid",
    "home_id": 161,
    "away_id": 530,
    "home_score": 1,
    "away_score": 2,
    "points": 0,
    "is_home": true,
    "corners_for": 0,
    "corners_ag": 0
  },
  {
    "date": "2021-09-14T19:00:00+00:00",
    "season": 2021,
    "home": "Lille",
    "away": "VfL Wolfsburg",
    "home_id": 79,
    "away_id": 161,
    "home_score": 0,
    "away_score": 0,
    "points": 1,
    "is_home": false,
    "corners_for": 0,
    "corners_ag": 0
  },
  {
    "date": "2021-09-29T19:00:00+00:00",
    "season": 2021,
    "home": "VfL Wolfsburg",
    "away": "Sevilla",
    "home_id": 161,
    "away_id": 536,
    "home_score": 1,
    "away_score": 1,
    "points": 1,
    "is_home": true,
    "corners_for": 0,
    "corners_ag": 0
  },
  {
    "date": "2021-10-20T16:45:00+00:00",
    "season": 2021,
    "home": "Red Bull Salzburg",
    "away": "VfL Wolfsburg",
    "home_id": 571,
    "away_id": 161,
    "home_score": 3,
    "away_score": 1,
    "points": 0,
    "is_home": false,
    "corners_for": 0,
    "corners_ag": 0
  },
  {
    "date": "2021-11-02T17:45:00+00:00",
    "season": 2021,
    "home": "VfL Wolfsburg",
    "away": "Red Bull Salzburg",
    "home_id": 161,
    "away_id": 571,
    "home_score": 2,
    "away_score": 1,
    "points": 3,
    "is_home": true,
    "corners_for": 0,
    "corners_ag": 0
  },
  {
    "date": "2021-11-23T20:00:00+00:00",
    "season": 2021,
    "home": "Sevilla",
    "away": "VfL Wolfsburg",
    "home_id": 536,
    "away_id": 161,
    "home_score": 2,
    "away_score": 0,
    "points": 0,
    "is_home": false,
    "corners_for": 0,
    "corners_ag": 0
  },
  {
    "date": "2021-12-08T20:00:00+00:00",
    "season": 2021,
    "home": "VfL Wolfsburg",
    "away": "Lille",
    "home_id": 161,
    "away_id": 79,
    "home_score": 1,
    "away_score": 3,
    "points": 0,
    "is_home": true,
    "corners_for": 0,
    "corners_ag": 0
  },
  {
    "date": "2021-10-06T00:00:00+00:00",
    "season": 2021,
    "home": "VfL Wolfsburg",
    "away": "Hamburger SV",
    "home_id": 161,
    "away_id": 175,
    "home_score": 4,
    "away_score": 1,
    "points": 3,
    "is_home": true,
    "corners_for": 0,
    "corners_ag": 0
  },
  {
    "date": "2021-09-01T00:00:00+00:00",
    "season": 2021,
    "home": "VfL Wolfsburg",
    "away": "Hannover 96",
    "home_id": 161,
    "away_id": 166,
    "home_score": 3,
    "away_score": 3,
    "points": 1,
    "is_home": true,
    "corners_for": 0,
    "corners_ag": 0
  },
  {
    "date": "2021-11-10T12:00:00+00:00",
    "season": 2021,
    "home": "VfL Wolfsburg",
    "away": "Hansa Rostock",
    "home_id": 161,
    "away_id": 1321,
    "home_score": 1,
    "away_score": 3,
    "points": 0,
    "is_home": true,
    "corners_for": 0,
    "corners_ag": 0
  },
  {
    "date": "2022-01-04T00:00:00+00:00",
    "season": 2021,
    "home": "VfL Wolfsburg",
    "away": "SC Paderborn 07",
    "home_id": 161,
    "away_id": 185,
    "home_score": 5,
    "away_score": 4,
    "points": 3,
    "is_home": true,
    "corners_for": 0,
    "corners_ag": 0
  }
]