[
  {
    "date": "2021-08-14T17:30:00+00:00",
    "season": 2021,
    "home": "Mallorca",
    "away": "Real Betis",
    "home_id": 798,
    "away_id": 543,
    "home_score": 1,
    "away_score": 1,
    "points": 1,
    "is_home": false,
    "corners_for": 0,
    "corners_ag": 0
  },
  {
    "date": "2021-08-20T19:00:00+00:00",
    "season": 2021,
    "home": "Real Betis",
    "away": "Cadiz",
    "home_id": 543,
    "away_id": 724,
    "home_score": 1,
    "away_score": 1,
    "points": 1,
    "is_home": true,
    "corners_for": 0,
    "corners_ag": 0
  },
  {
    "date": "2021-08-28T20:00:00+00:00",
    "season": 2021,
    "home": "Real Betis",
    "away": "Real Madrid",
    "home_id": 543,
    "away_id": 541,
    "home_score": 0,
    "away_score": 1,
    "points": 0,
    "is_home": true,
    "corners_for": 0,
    "corners_ag": 0
  },
  {
    "date": "2021-09-13T20:00:00+00:00",
    "season": 2021,
    "home": "Granada CF",
    "away": "Real Betis",
    "home_id": 715,
    "away_id": 543,
    "home_score": 1,
    "away_score": 2,
    "points": 3,
    "is_home": false,
    "corners_for": 0,
    "corners_ag": 0
  },
  {
    "date": "2021-09-19T16:30:00+00:00",
    "season": 2021,
    "home": "Real Betis",
    "away": "Espanyol",
    "home_id": 543,
    "away_id": 540,
    "home_score": 2,
    "away_score": 2,
    "points": 1,
    "is_home": true,
    "corners_for": 0,
    "corners_ag": 0
  },
  {
    "date": "2021-09-23T17:30:00+00:00",
    "season": 2021,
    "home": "Osasuna",
    "away": "Real Betis",
    "home_id": 727,
    "away_id": 543,
    "home_score": 1,
    "away_score": 3,
    "points": 3,
    "is_home": false,
    "corners_for": 0,
    "corners_ag": 0
  },
  {
    "date": "2021-09-26T19:00:00+00:00",
    "season": 2021,
    "home": "Real Betis",
    "away": "Getafe",
    "home_id": 543,
    "away_id": 546,
    "home_score": 2,
    "away_score": 0,
    "points": 3,
    "is_home": true,
    "corners_for": 0,
    "corners_ag": 0
  },
  {
    "date": "2021-10-03T16:30:00+00:00",
    "season": 2021,
    "home": "Villarreal",
    "away": "Real Betis",
    "home_id": 533,
    "away_id": 543,
    "home_score": 2,
    "away_score": 0,
    "points": 0,
    "is_home": false,
    "corners_for": 0,
    "corners_ag": 0
  },
  {
    "date": "2021-10-18T17:00:00+00:00",
    "season": 2021,
    "home": "Alaves",
    "away": "Real Betis",
    "home_id": 542,
    "away_id": 543,
    "home_score": 0,
    "away_score": 1,
    "points": 3,
    "is_home": false,
    "corners_for": 0,
    "corners_ag": 0
  },
  {
    "date": "2021-10-24T16:30:00+00:00",
    "season": 2021,
    "home": "Real Betis",
    "away": "Rayo Vallecano",
    "home_id": 543,
    "away_id": 728,
    "home_score": 3,
    "away_score": 2,
    "points": 3,
    "is_home": true,
    "corners_for": 0,
    "corners_ag": 0
  },
  {
    "date": "2021-10-27T18:00:00+00:00",
    "season": 2021,
    "home": "Real Betis",
    "away": "Valencia",
    "home_id": 543,
    "away_id": 532,
    "home_score": 4,
    "away_score": 1,
    "points": 3,
    "is_home": true,
    "corners_for": 0,
    "corners_ag": 0
  },
  {
    "date": "2021-10-31T15:15:00+00:00",
    "season": 2021,
    "home": "Atletico Madrid",
    "away": "Real Betis",
    "home_id": 530,
    "away_id": 543,
    "home_score": 3,
    "away_score": 0,
    "points": 0,
    "is_home": false,
    "corners_for": 0,
    "corners_ag": 0
  },
  {
    "date": "2021-11-07T20:00:00+00:00",
    "season": 2021,
    "home": "Real Betis",
    "away": "Sevilla",
    "home_id": 543,
    "away_id": 536,
    "home_score": 0,
    "away_score": 2,
    "points": 0,
    "is_home": true,
    "corners_for": 0,
    "corners_ag": 0
  },
  {
    "date": "2021-11-21T17:30:00+00:00",
    "season": 2021,
    "home": "Elche",
    "away": "Real Betis",
    "home_id": 797,
    "away_id": 543,
    "home_score": 0,
    "away_score": 3,
    "points": 3,
    "is_home": false,
    "corners_for": 0,
    "corners_ag": 0
  },
  {
    "date": "2021-11-28T13:00:00+00:00",
    "season": 2021,
    "home": "Real Betis",
    "away": "Levante",
    "home_id": 543,
    "away_id": 539,
    "home_score": 3,
    "away_score": 1,
    "points": 3,
    "is_home": true,
    "corners_for": 0,
    "corners_ag": 0
  },
  {
    "date": "2021-12-04T15:15:00+00:00",
    "season": 2021,
    "home": "Barcelona",
    "away": "Real Betis",
    "home_id": 529,
    "away_id": 543,
    "home_score": 0,
    "away_score": 1,
    "points": 3,
    "is_home": false,
    "corners_for": 0,
    "corners_ag": 0
  },
  {
    "date": "2021-12-12T17:30:00+00:00",
    "season": 2021,
    "home": "Real Betis",
    "away": "Real Sociedad",
    "home_id": 543,
    "away_id": 548,
    "home_score": 4,
    "away_score": 0,
    "points": 3,
    "is_home": true,
    "corners_for": 0,
    "corners_ag": 0
  },
  {
    "date": "2021-12-19T15:15:00+00:00",
    "season": 2021,
    "home": "Athletic Club",
    "away": "Real Betis",
    "home_id": 531,
    "away_id": 543,
    "home_score": 3,
    "away_score": 2,
    "points": 0,
    "is_home": false,
    "corners_for": 0,
    "corners_ag": 0
  },
  {
    "date": "2022-01-02T17:30:00+00:00",
    "season": 2021,
    "home": "Real Betis",
    "away": "Celta Vigo",
    "home_id": 543,
    "away_id": 538,
    "home_score": 0,
    "away_score": 2,
    "points": 0,
    "is_home": true,
    "corners_for": 0,
    "corners_ag": 0
  },
  {
    "date": "2022-01-09T13:00:00+00:00",
    "season": 2021,
    "home": "Rayo Vallecano",
    "away": "Real Betis",
    "home_id": 728,
    "away_id": 543,
    "home_score": 1,
    "away_score": 1,
    "points": 1,
    "is_home": false,
    "corners_for": 0,
    "corners_ag": 0
  },
  {
    "date": "2022-01-18T19:00:00+00:00",
    "season": 2021,
    "home": "Real Betis",
    "away": "Alaves",
    "home_id": 543,
    "away_id": 542,
    "home_score": 4,
    "away_score": 0,
    "points": 3,
    "is_home": true,
    "corners_for": 0,
    "corners_ag": 0
  },
  {
    "date": "2022-01-21T20:00:00+00:00",
    "season": 2021,
    "home": "Espanyol",
    "away": "Real Betis",
    "home_id": 540,
    "away_id": 543,
    "home_score": 1,
    "away_score": 4,
    "points": 3,
    "is_home": false,
    "corners_for": 0,
    "corners_ag": 0
  },
  {
    "date": "2022-02-06T17:30:00+00:00",
    "season": 2021,
    "home": "Real Betis",
    "away": "Villarreal",
    "home_id": 543,
    "away_id": 533,
    "home_score": 0,
    "away_score": 2,
    "points": 0,
    "is_home": true,
    "corners_for": 0,
    "corners_ag": 0
  },
  {
    "date": "2022-02-13T15:15:00+00:00",
    "season": 2021,
    "home": "Levante",
    "away": "Real Betis",
    "home_id": 539,
    "away_id": 543,
    "home_score": 2,
    "away_score": 4,
    "points": 3,
    "is_home": false,
    "corners_for": 0,
    "corners_ag": 0
  },
  {
    "date": "2022-02-20T17:30:00+00:00",
    "season": 2021,
    "home": "Real Betis",
    "away": "Mallorca",
    "home_id": 543,
    "away_id": 798,
    "home_score": 2,
    "away_score": 1,
    "points": 3,
    "is_home": true,
    "corners_for": 0,
    "corners_ag": 0
  },
  {
    "date": "2022-02-27T15:15:00+00:00",
    "season": 2021,
    "home": "Sevilla",
    "away": "Real Betis",
    "home_id": 536,
    "away_id": 543,
    "home_score": 2,
    "away_score": 1,
    "points": 0,
    "is_home": false,
    "corners_for": 0,
    "corners_ag": 0
  },
  {
    "date": "2022-03-06T20:00:00+00:00",
    "season": 2021,
    "home": "Real Betis",
    "away": "Atletico Madrid",
    "home_id": 543,
    "away_id": 530,
    "home_score": 1,
    "away_score": 3,
    "points": 0,
    "is_home": true,
    "corners_for": 0,
    "corners_ag": 0
  },
  {
    "date": "2022-03-13T15:15:00+00:00",
    "season": 2021,
    "home": "Real Betis",
    "away": "Athletic Club",
    "home_id": 543,
    "away_id": 531,
    "home_score": 1,
    "away_score": 0,
    "points": 3,
    "is_home": true,
    "corners_for": 0,
    "corners_ag": 0
  },
  {
    "date": "2022-03-20T15:15:00+00:00",
    "season": 2021,
    "home": "Celta Vigo",
    "away": "Real Betis",
    "home_id": 538,
    "away_id": 543,
    "home_score": 0,
    "away_score": 0,
    "points": 1,
    "is_home": false,
    "corners_for": 0,
    "corners_ag": 0
  },
  {
    "date": "2022-04-03T14:15:00+00:00",
    "season": 2021,
    "home": "Real Betis",
    "away": "Osasuna",
    "home_id": 543,
    "away_id": 727,
    "home_score": 4,
    "away_score": 1,
    "points": 3,
    "is_home": true,
    "corners_for": 0,
    "corners_ag": 0
  },
  {
    "date": "2022-04-09T12:00:00+00:00",
    "season": 2021,
    "home": "Cadiz",
    "away": "Real Betis",
    "home_id": 724,
    "away_id": 543,
    "home_score": 1,
    "away_score": 2,
    "points": 3,
    "is_home": false,
    "corners_for": 0,
    "corners_ag": 0
  },
  {
    "date": "2022-04-15T19:00:00+00:00",
    "season": 2021,
    "home": "Real Sociedad",
    "away": "Real Betis",
    "home_id": 548,
    "away_id": 543,
    "home_score": 0,
    "away_score": 0,
    "points": 1,
    "is_home": false,
    "corners_for": 0,
    "corners_ag": 0
  },
  {
    "date": "2022-04-19T19:00:00+00:00",
    "season": 2021,
    "home": "Real Betis",
    "away": "Elche",
    "home_id": 543,
    "away_id": 797,
    "home_score": 0,
    "away_score": 1,
    "points": 0,
    "is_home": true,
    "corners_for": 0,
    "corners_ag": 0
  },
  {
    "date": "2022-05-02T19:00:00+00:00",
    "season": 2021,
    "home": "Getafe",
    "away": "Real Betis",
    "home_id": 546,
    "away_id": 543,
    "home_score": 0,
    "away_score": 0,
    "points": 1,
    "is_home": false,
    "corners_for": 0,
    "corners_ag": 0
  },
  {
    "date": "2022-05-07T19:00:00+00:00",
    "season": 2021,
    "home": "Real Betis",
    "away": "Barcelona",
    "home_id": 543,
    "away_id": 529,
    "home_score": 1,
    "away_score": 2,
    "points": 0,
    "is_home": true,
    "corners_for": 0,
    "corners_ag": 0
  },
  {
    "date": "2022-05-10T17:00:00+00:00",
    "season": 2021,
    "home": "Valencia",
    "away": "Real Betis",
    "home_id": 532,
    "away_id": 543,
    "home_score": 0,
    "away_score": 3,
    "points": 3,
    "is_home": false,
    "corners_for": 0,
    "corners_ag": 0
  },
  {
    "date": "2022-05-15T17:30:00+00:00",
    "season": 2021,
    "home": "Real Betis",
    "away": "Granada CF",
    "home_id": 543,
    "away_id": 715,
    "home_score": 2,
    "away_score": 0,
    "points": 3,
    "is_home": true,
    "corners_for": 0,
    "corners_ag": 0
  },
  {
    "date": "2022-05-20T19:00:00+00:00",
    "season": 2021,
    "home": "Real Madrid",
    "away": "Real Betis",
    "home_id": 541,
    "away_id": 543,
    "home_score": 0,
    "away_score": 0,
    "points": 1,
    "is_home": false,
    "corners_for": 0,
    "corners_ag": 0
  },
  {
    "date": "2021-08-07T20:00:00+00:00",
    "season": 2021,
    "home": "Real Betis",
    "away": "AS Roma",
    "home_id": 543,
    "away_id": 497,
    "home_score": 5,
    "away_score": 2,
    "points": 3,
    "is_home": true,
    "corners_for": 0,
    "corners_ag": 0
  },
  {
    "date": "2021-07-17T13:00:00+00:00",
    "season": 2021,
    "home": "FC Winterthur",
    "away": "Real Betis",
    "home_id": 2180,
    "away_id": 543,
    "home_score": 0,
    "away_score": 4,
    "points": 3,
    "is_home": false,
    "corners_for": 0,
    "corners_ag": 0
  },
  {
    "date": "2021-07-24T17:00:00+00:00",
    "season": 2021,
    "home": "Real Betis",
    "away": "Wolves",
    "home_id": 543,
    "away_id": 39,
    "home_score": 0,
    "away_score": 1,
    "points": 0,
    "is_home": true,
    "corners_for": 0,
    "corners_ag": 0
  },
  {
    "date": "2021-07-28T18:00:00+00:00",
    "season": 2021,
    "home": "Derby",
    "away": "Real Betis",
    "home_id": 69,
    "away_id": 543,
    "home_score": 1,
    "away_score": 0,
    "points": 0,
    "is_home": false,
    "corners_for": 0,
    "corners_ag": 0
  },
  {
    "date": "2021-07-31T00:00:00+00:00",
    "season": 2021,
    "home": "Leeds",
    "away": "Real Betis",
    "home_id": 63,
    "away_id": 543,
    "home_score": 2,
    "away_score": 3,
    "points": 3,
    "is_home": false,
    "corners_for": 0,
    "corners_ag": 0
  },
  {
    "date": "2021-08-04T17:00:00+00:00",
    "season": 2021,
    "home": "Real Betis",
    "away": "Almeria",
    "home_id": 543,
    "away_id": 723,
    "home_score": 1,
    "away_score": 2,
    "points": 0,
    "is_home": true,
    "corners_for": 0,
    "corners_ag": 0
  },
  {
    "date": "2021-08-04T00:00:00+00:00",
    "season": 2021,
    "home": "Almeria",
    "away": "Real Betis",
    "home_id": 723,
    "away_id": 543,
    "home_score": 2,
    "away_score": 1,
    "points": 0,
    "is_home": false,
    "corners_for": 0,
    "corners_ag": 0
  },
  {
    "date": "2021-09-16T16:45:00+00:00",
    "season": 2021,
    "home": "Real Betis",
    "away": "Celtic",
    "home_id": 543,
    "away_id": 247,
    "home_score": 4,
    "away_score": 3,
    "points": 3,
    "is_home": true,
    "corners_for": 0,
    "corners_ag": 0
  },
  {
    "date": "2021-09-30T19:00:00+00:00",
    "season": 2021,
    "home": "Ferencvarosi TC",
    "away": "Real Betis",
    "home_id": 651,
    "away_id": 543,
    "home_score": 1,
    "away_score": 3,
    "points": 3,
    "is_home": false,
    "corners_for": 0,
    "corners_ag": 0
  },
  {
    "date": "2021-10-21T16:45:00+00:00",
    "season": 2021,
    "home": "Real Betis",
    "away": "Bayer Leverkusen",
    "home_id": 543,
    "away_id": 168,
    "home_score": 1,
    "away_score": 1,
    "points": 1,
    "is_home": true,
    "corners_for": 0,
    "corners_ag": 0
  },
  {
    "date": "2021-11-04T20:00:00+00:00",
    "season": 2021,
    "home": "Bayer Leverkusen",
    "away": "Real Betis",
    "home_id": 168,
    "away_id": 543,
    "home_score": 4,
    "away_score": 0,
    "points": 0,
    "is_home": false,
    "corners_for": 0,
    "corners_ag": 0
  },
  {
    "date": "2021-11-25T17:45:00+00:00",
    "season": 2021,
    "home": "Real Betis",
    "away": "Ferencvarosi TC",
    "home_id": 543,
    "away_id": 651,
    "home_score": 2,
    "away_score": 0,
    "points": 3,
    "is_home": true,
    "corners_for": 0,
    "corners_ag": 0
  },
  {
    "date": "2021-12-09T20:00:00+00:00",
    "season": 2021,
    "home": "Celtic",
    "away": "Real Betis",
    "home_id": 247,
    "away_id": 543,
    "home_score": 3,
    "away_score": 2,
    "points": 0,
    "is_home": false,
    "corners_for": 0,
    "corners_ag": 0
  },
  {
    "date": "2021-12-01T20:00:00+00:00",
    "season": 2021,
    "home": "CFI Alicante",
    "away": "Real Betis",
    "home_id": 18089,
    "away_id": 543,
    "home_score": 0,
    "away_score": 4,
    "points": 3,
    "is_home": false,
    "corners_for": 0,
    "corners_ag": 0
  },
  {
    "date": "2022-02-17T17:45:00+00:00",
    "season": 2021,
    "home": "Zenit Saint Petersburg",
    "away": "Real Betis",
    "home_id": 596,
    "away_id": 543,
    "home_score": 2,
    "away_score": 3,
    "points": 3,
    "is_home": false,
    "corners_for": 0,
    "corners_ag": 0
  },
  {
    "date": "2022-02-24T20:00:00+00:00",
    "season": 2021,
    "home": "Real Betis",
    "away": "Zenit Saint Petersburg",
    "home_id": 543,
    "away_id": 596,
    "home_score": 0,
    "away_score": 0,
    "points": 1,
    "is_home": true,
    "corners_for": 0,
    "corners_ag": 0
  },
  {
    "date": "2022-01-05T19:00:00+00:00",
    "season": 2021,
    "home": "Valladolid",
    "away": "Real Betis",
    "home_id": 720,
    "away_id": 543,
    "home_score": 0,
    "away_score": 3,
    "points": 3,
    "is_home": false,
    "corners_for": 0,
    "corners_ag": 0
  },
  {
    "date": "2022-01-16T20:30:00+00:00",
    "season": 2021,
    "home": "Real Betis",
    "away": "Sevilla",
    "home_id": 543,
    "away_id": 536,
    "home_score": 2,
    "away_score": 1,
    "points": 3,
    "is_home": true,
    "corners_for": 0,
    "corners_ag": 0
  },
  {
    "date": "2022-02-03T19:00:00+00:00",
    "season": 2021,
    "home": "Real Sociedad",
    "away": "Real Betis",
    "home_id": 548,
    "away_id": 543,
    "home_score": 0,
    "away_score": 4,
    "points": 3,
    "is_home": false,
    "corners_for": 0,
    "corners_ag": 0
  },
  {
    "date": "2022-02-09T20:00:00+00:00",
    "season": 2021,
    "home": "Rayo Vallecano",
    "away": "Real Betis",
    "home_id": 728,
    "away_id": 543,
    "home_score": 1,
    "away_score": 2,
    "points": 3,
    "is_home": false,
    "corners_for": 0,
    "corners_ag": 0
  },
  {
    "date": "2022-03-03T20:00:00+00:00",
    "season": 2021,
    "home": "Real Betis",
    "away": "Rayo Vallecano",
    "home_id": 543,
    "away_id": 728,
    "home_score": 1,
    "away_score": 1,
    "points": 1,
    "is_home": true,
    "corners_for": 0,
    "corners_ag": 0
  },
  {
    "date": "2022-03-09T17:45:00+00:00",
    "season": 2021,
    "home": "Real Betis",
    "away": "Eintracht Frankfurt",
    "home_id": 543,
    "away_id": 169,
    "home_score": 1,
    "away_score": 2,
    "points": 0,
    "is_home": true,
    "corners_for": 0,
    "corners_ag": 0
  }
]