[
  {
    "date": "2021-07-23T00:00:00+00:00",
    "season": 2021,
    "home": "Bayer Leverkusen",
    "away": "SC Freiburg",
    "home_id": 168,
    "away_id": 160,
    "home_score": 0,
    "away_score": 0,
    "points": 1,
    "is_home": true,
    "corners_for": 0,
    "corners_ag": 0
  },
  {
    "date": "2021-07-28T14:00:00+00:00",
    "season": 2021,
    "home": "Bayer Leverkusen",
    "away": "Utrecht",
    "home_id": 168,
    "away_id": 207,
    "home_score": 1,
    "away_score": 5,
    "points": 0,
    "is_home": true,
    "corners_for": 0,
    "corners_ag": 0
  },
  {
    "date": "2021-07-31T00:00:00+00:00",
    "season": 2021,
    "home": "Bayer Leverkusen",
    "away": "Rot-weiss Oberhausen",
    "home_id": 168,
    "away_id": 1658,
    "home_score": 3,
    "away_score": 1,
    "points": 3,
    "is_home": true,
    "corners_for": 0,
    "corners_ag": 0
  },
  {
    "date": "2021-08-07T13:30:00+00:00",
    "season": 2021,
    "home": "Lokomotive Leipzig",
    "away": "Bayer Leverkusen",
    "home_id": 9355,
    "away_id": 168,
    "home_score": 0,
    "away_score": 3,
    "points": 3,
    "is_home": false,
    "corners_for": 0,
    "corners_ag": 0
  },
  {
    "date": "2021-08-14T13:30:00+00:00",
    "season": 2021,
    "home": "Union Berlin",
    "away": "Bayer Leverkusen",
    "home_id": 182,
    "away_id": 168,
    "home_score": 1,
    "away_score": 1,
    "points": 1,
    "is_home": false,
    "corners_for": 0,
    "corners_ag": 0
  },
  {
    "date": "2021-08-21T16:30:00+00:00",
    "season": 2021,
    "home": "Bayer Leverkusen",
    "away": "Borussia Monchengladbach",
    "home_id": 168,
    "away_id": 163,
    "home_score": 4,
    "away_score": 0,
    "points": 3,
    "is_home": true,
    "corners_for": 0,
    "corners_ag": 0
  },
  {
    "date": "2021-08-28T13:30:00+00:00",
    "season": 2021,
    "home": "FC Augsburg",
    "away": "Bayer Leverkusen",
    "home_id": 170,
    "away_id": 168,
    "home_score": 1,
    "away_score": 4,
    "points": 3,
    "is_home": false,
    "corners_for": 0,
    "corners_ag": 0
  },
  {
    "date": "2021-09-11T13:30:00+00:00",
    "season": 2021,
    "home": "Bayer Leverkusen",
    "away": "Borussia Dortmund",
    "home_id": 168,
    "away_id": 165,
    "home_score": 3,
    "away_score": 4,
    "points": 0,
    "is_home": true,
    "corners_for": 0,
    "corners_ag": 0
  },
  {
    "date": "2021-09-16T16:45:00+00:00",
    "season": 2021,
    "home": "Bayer Leverkusen",
    "away": "Ferencvarosi TC",
    "home_id": 168,
    "away_id": 651,
    "home_score": 2,
    "away_score": 1,
    "points": 3,
    "is_home": true,
    "corners_for": 0,
    "corners_ag": 0
  },
  {
    "date": "2021-09-19T13:30:00+00:00",
    "season": 2021,
    "home": "VfB Stuttgart",
    "away": "Bayer Leverkusen",
    "home_id": 172,
    "away_id": 168,
    "home_score": 1,
    "away_score": 3,
    "points": 3,
    "is_home": false,
    "corners_for": 0,
    "corners_ag": 0
  },
  {
    "date": "2021-09-25T13:30:00+00:00",
    "season": 2021,
    "home": "Bayer Leverkusen",
    "away": "FSV Mainz 05",
    "home_id": 168,
    "away_id": 164,
    "home_score": 1,
    "away_score": 0,
    "points": 3,
    "is_home": true,
    "corners_for": 0,
    "corners_ag": 0
  },
  {
    "date": "2021-09-30T19:00:00+00:00",
    "season": 2021,
    "home": "Celtic",
    "away": "Bayer Leverkusen",
    "home_id": 247,
    "away_id": 168,
    "home_score": 0,
    "away_score": 4,
    "points": 3,
    "is_home": false,
    "corners_for": 0,
    "corners_ag": 0
  },
  {
    "date": "2021-10-03T17:30:00+00:00",
    "season": 2021,
    "home": "Arminia Bielefeld",
    "away": "Bayer Leverkusen",
    "home_id": 188,
    "away_id": 168,
    "home_score": 0,
    "away_score": 4,
    "points": 3,
    "is_home": false,
    "corners_for": 0,
    "corners_ag": 0
  },
  {
    "date": "2021-10-17T13:30:00+00:00",
    "season": 2021,
    "home": "Bayer Leverkusen",
    "away": "Bayern Munich",
    "home_id": 168,
    "away_id": 157,
    "home_score": 1,
    "away_score": 5,
    "points": 0,
    "is_home": true,
    "corners_for": 0,
    "corners_ag": 0
  },
  {
    "date": "2021-10-21T16:45:00+00:00",
    "season": 2021,
    "home": "Real Betis",
    "away": "Bayer Leverkusen",
    "home_id": 543,
    "away_id": 168,
    "home_score": 1,
    "away_score": 1,
    "points": 1,
    "is_home": false,
    "corners_for": 0,
    "corners_ag": 0
  },
  {
    "date": "2021-10-24T13:30:00+00:00",
    "season": 2021,
    "home": "1. FC Köln",
    "away": "Bayer Leverkusen",
    "home_id": 192,
    "away_id": 168,
    "home_score": 2,
    "away_score": 2,
    "points": 1,
    "is_home": false,
    "corners_for": 0,
    "corners_ag": 0
  },
  {
    "date": "2021-10-27T16:30:00+00:00",
    "season": 2021,
    "home": "Bayer Leverkusen",
    "away": "Karlsruher SC",
    "home_id": 168,
    "away_id": 785,
    "home_score": 1,
    "away_score": 2,
    "points": 0,
    "is_home": true,
    "corners_for": 0,
    "corners_ag": 0
  },
  {
    "date": "2021-10-30T13:30:00+00:00",
    "season": 2021,
    "home": "Bayer Leverkusen",
    "away": "VfL Wolfsburg",
    "home_id": 168,
    "away_id": 161,
    "home_score": 0,
    "away_score": 2,
    "points": 0,
    "is_home": true,
    "corners_for": 0,
    "corners_ag": 0
  },
  {
    "date": "2021-11-04T20:00:00+00:00",
    "season": 2021,
    "home": "Bayer Leverkusen",
    "away": "Real Betis",
    "home_id": 168,
    "away_id": 543,
    "home_score": 4,
    "away_score": 0,
    "points": 3,
    "is_home": true,
    "corners_for": 0,
    "corners_ag": 0
  },
  {
    "date": "2021-11-07T14:30:00+00:00",
    "season": 2021,
    "home": "Hertha Berlin",
    "away": "Bayer Leverkusen",
    "home_id": 159,
    "away_id": 168,
    "home_score": 1,
    "away_score": 1,
    "points": 1,
    "is_home": false,
    "corners_for": 0,
    "corners_ag": 0
  },
  {
    "date": "2021-11-20T14:30:00+00:00",
    "season": 2021,
    "home": "Bayer Leverkusen",
    "away": "Vfl Bochum",
    "home_id": 168,
    "away_id": 176,
    "home_score": 1,
    "away_score": 0,
    "points": 3,
    "is_home": true,
    "corners_for": 0,
    "corners_ag": 0
  },
  {
    "date": "2021-11-25T17:45:00+00:00",
    "season": 2021,
    "home": "Bayer Leverkusen",
    "away": "Celtic",
    "home_id": 168,
    "away_id": 247,
    "home_score": 3,
    "away_score": 2,
    "points": 3,
    "is_home": true,
    "corners_for": 0,
    "corners_ag": 0
  },
  {
    "date": "2021-11-28T16:30:00+00:00",
    "season": 2021,
    "home": "RB Leipzig",
    "away": "Bayer Leverkusen",
    "home_id": 173,
    "away_id": 168,
    "home_score": 1,
    "away_score": 3,
    "points": 3,
    "is_home": false,
    "corners_for": 0,
    "corners_ag": 0
  },
  {
    "date": "2021-12-04T14:30:00+00:00",
    "season": 2021,
    "home": "Bayer Leverkusen",
    "away": "SpVgg Greuther Furth",
    "home_id": 168,
    "away_id": 178,
    "home_score": 7,
    "away_score": 1,
    "points": 3,
    "is_home": true,
    "corners_for": 0,
    "corners_ag": 0
  },
  {
    "date": "2021-12-09T20:00:00+00:00",
    "season": 2021,
    "home": "Ferencvarosi TC",
    "away": "Bayer Leverkusen",
    "home_id": 651,
    "away_id": 168,
    "home_score": 1,
    "away_score": 0,
    "points": 0,
    "is_home": false,
    "corners_for": 0,
    "corners_ag": 0
  },
  {
    "date": "2021-12-12T16:30:00+00:00",
    "season": 2021,
    "home": "Eintracht Frankfurt",
    "away": "Bayer Leverkusen",
    "home_id": 169,
    "away_id": 168,
    "home_score": 5,
    "away_score": 2,
    "points": 0,
    "is_home": false,
    "corners_for": 0,
    "corners_ag": 0
  },
  {
    "date": "2021-12-15T19:30:00+00:00",
    "season": 2021,
    "home": "Bayer Leverkusen",
    "away": "1899 Hoffenheim",
    "home_id": 168,
    "away_id": 167,
    "home_score": 2,
    "away_score": 2,
    "points": 1,
    "is_home": true,
    "corners_for": 0,
    "corners_ag": 0
  },
  {
    "date": "2021-12-19T14:30:00+00:00",
    "season": 2021,
    "home": "SC Freiburg",
    "away": "Bayer Leverkusen",
    "home_id": 160,
    "away_id": 168,
    "home_score": 2,
    "away_score": 1,
    "points": 0,
    "is_home": false,
    "corners_for": 0,
    "corners_ag": 0
  },
  {
    "date": "2022-01-08T14:30:00+00:00",
    "season": 2021,
    "home": "Bayer Leverkusen",
    "away": "Union Berlin",
    "home_id": 168,
    "away_id": 182,
    "home_score": 2,
    "away_score": 2,
    "points": 1,
    "is_home": true,
    "corners_for": 0,
    "corners_ag": 0
  },
  {
    "date": "2022-01-15T17:30:00+00:00",
    "season": 2021,
    "home": "Borussia Monchengladbach",
    "away": "Bayer Leverkusen",
    "home_id": 163,
    "away_id": 168,
    "home_score": 1,
    "away_score": 2,
    "points": 3,
    "is_home": false,
    "corners_for": 0,
    "corners_ag": 0
  },
  {
    "date": "2022-01-22T14:30:00+00:00",
    "season": 2021,
    "home": "Bayer Leverkusen",
    "away": "FC Augsburg",
    "home_id": 168,
    "away_id": 170,
    "home_score": 5,
    "away_score": 1,
    "points": 3,
    "is_home": true,
    "corners_for": 0,
    "corners_ag": 0
  },
  {
    "date": "2022-02-06T14:30:00+00:00",
    "season": 2021,
    "home": "Borussia Dortmund",
    "away": "Bayer Leverkusen",
    "home_id": 165,
    "away_id": 168,
    "home_score": 2,
    "away_score": 5,
    "points": 3,
    "is_home": false,
    "corners_for": 0,
    "corners_ag": 0
  },
  {
    "date": "2022-02-12T17:30:00+00:00",
    "season": 2021,
    "home": "Bayer Leverkusen",
    "away": "VfB Stuttgart",
    "home_id": 168,
    "away_id": 172,
    "home_score": 4,
    "away_score": 2,
    "points": 3,
    "is_home": true,
    "corners_for": 0,
    "corners_ag": 0
  },
  {
    "date": "2022-02-18T19:30:00+00:00",
    "season": 2021,
    "home": "FSV Mainz 05",
    "away": "Bayer Leverkusen",
    "home_id": 164,
    "away_id": 168,
    "home_score": 3,
    "away_score": 2,
    "points": 0,
    "is_home": false,
    "corners_for": 0,
    "corners_ag": 0
  },
  {
    "date": "2022-02-26T14:30:00+00:00",
    "season": 2021,
    "home": "Bayer Leverkusen",
    "away": "Arminia Bielefeld",
    "home_id": 168,
    "away_id": 188,
    "home_score": 3,
    "away_score": 0,
    "points": 3,
    "is_home": true,
    "corners_for": 0,
    "corners_ag": 0
  },
  {
    "date": "2022-03-05T14:30:00+00:00",
    "season": 2021,
    "home": "Bayern Munich",
    "away": "Bayer Leverkusen",
    "home_id": 157,
    "away_id": 168,
    "home_score": 1,
    "away_score": 1,
    "points": 1,
    "is_home": false,
    "corners_for": 0,
    "corners_ag": 0
  },
  {
    "date": "2022-03-10T20:00:00+00:00",
    "season": 2021,
    "home": "Atalanta",
    "away": "Bayer Leverkusen",
    "home_id": 499,
    "away_id": 168,
    "home_score": 3,
    "away_score": 2,
    "points": 0,
    "is_home": false,
    "corners_for": 0,
    "corners_ag": 0
  },
  {
    "date": "2022-03-13T14:30:00+00:00",
    "season": 2021,
    "home": "Bayer Leverkusen",
    "away": "1. FC Köln",
    "home_id": 168,
    "away_id": 192,
    "home_score": 0,
    "away_score": 1,
    "points": 0,
    "is_home": true,
    "corners_for": 0,
    "corners_ag": 0
  },
  {
    "date": "2022-03-17T17:45:00+00:00",
    "season": 2021,
    "home": "Bayer Leverkusen",
    "away": "Atalanta",
    "home_id": 168,
    "away_id": 499,
    "home_score": 0,
    "away_score": 1,
    "points": 0,
    "is_home": true,
    "corners_for": 0,
    "corners_ag": 0
  },
  {
    "date": "2022-03-20T16:30:00+00:00",
    "season": 2021,
    "home": "VfL Wolfsburg",
    "away": "Bayer Leverkusen",
    "home_id": 161,
    "away_id": 168,
    "home_score": 0,
    "away_score": 2,
    "points": 3,
    "is_home": false,
    "corners_for": 0,
    "corners_ag": 0
  },
  {
    "date": "2022-04-02T13:30:00+00:00",
    "season": 2021,
    "home": "Bayer Leverkusen",
    "away": "Hertha Berlin",
    "home_id": 168,
    "away_id": 159,
    "home_score": 2,
    "away_score": 1,
    "points": 3,
    "is_home": true,
    "corners_for": 0,
    "corners_ag": 0
  },
  {
    "date": "2022-04-10T13:30:00+00:00",
    "season": 2021,
    "home": "Vfl Bochum",
    "away": "Bayer Leverkusen",
    "home_id": 176,
    "away_id": 168,
    "home_score": 0,
    "away_score": 0,
    "points": 1,
    "is_home": false,
    "corners_for": 0,
    "corners_ag": 0
  },
  {
    "date": "2022-04-17T17:30:00+00:00",
    "season": 2021,
    "home": "Bayer Leverkusen",
    "away": "RB Leipzig",
    "home_id": 168,
    "away_id": 173,
    "home_score": 0,
    "away_score": 1,
    "points": 0,
    "is_home": true,
    "corners_for": 0,
    "corners_ag": 0
  },
  {
    "date": "2022-04-23T13:30:00+00:00",
    "season": 2021,
    "home": "SpVgg Greuther Furth",
    "away": "Bayer Leverkusen",
    "home_id": 178,
    "away_id": 168,
    "home_score": 1,
    "away_score": 4,
    "points": 3,
    "is_home": false,
    "corners_for": 0,
    "corners_ag": 0
  },
  {
    "date": "2022-05-02T18:30:00+00:00",
    "season": 2021,
    "home": "Bayer Leverkusen",
    "away": "Eintracht Frankfurt",
    "home_id": 168,
    "away_id": 169,
    "home_score": 2,
    "away_score": 0,
    "points": 3,
    "is_home": true,
    "corners_for": 0,
    "corners_ag": 0
  },
  {
    "date": "2022-05-07T13:30:00+00:00",
    "season": 2021,
    "home": "1899 Hoffenheim",
    "away": "Bayer Leverkusen",
    "home_id": 167,
    "away_id": 168,
    "home_score": 2,
    "away_score": 4,
    "points": 3,
    "is_home": false,
    "corners_for": 0,
    "corners_ag": 0
  },
  {
    "date": "2022-05-14T13:30:00+00:00",
    "season": 2021,
    "home": "Bayer Leverkusen",
    "away": "SC Freiburg",
    "home_id": 168,
    "away_id": 160,
    "home_score": 2,
    "away_score": 1,
    "points": 3,
    "is_home": true,
    "corners_for": 0,
    "corners_ag": 0
  },
  {
    "date": "2022-07-09T13:00:00+00:00",
    "season": 2022,
    "home": "Bayer Leverkusen",
    "away": "MSV Duisburg",
    "home_id": 168,
    "away_id": 187,
    "home_score": 6,
    "away_score": 1,
    "points": 3,
    "is_home": true,
    "corners_for": 0,
    "corners_ag": 0
  },
  {
    "date": "2022-07-17T15:00:00+00:00",
    "season": 2022,
    "home": "Bayer Leverkusen",
    "away": "Panathinaikos",
    "home_id": 168,
    "away_id": 617,
    "home_score": 0,
    "away_score": 0,
    "points": 1,
    "is_home": true,
    "corners_for": 0,
    "corners_ag": 0
  },
  {
    "date": "2022-07-21T16:00:00+00:00",
    "season": 2022,
    "home": "Udinese",
    "away": "Bayer Leverkusen",
    "home_id": 494,
    "away_id": 168,
    "home_score": 1,
    "away_score": 2,
    "points": 3,
    "is_home": false,
    "corners_for": 0,
    "corners_ag": 0
  },
  {
    "date": "2022-07-30T13:31:00+00:00",
    "season": 2022,
    "home": "SV Elversberg",
    "away": "Bayer Leverkusen",
    "home_id": 1660,
    "away_id": 168,
    "home_score": 4,
    "away_score": 3,
    "points": 0,
    "is_home": false,
    "corners_for": 0,
    "corners_ag": 0
  },
  {
    "date": "2022-08-06T16:30:00+00:00",
    "season": 2022,
    "home": "Borussia Dortmund",
    "away": "Bayer Leverkusen",
    "home_id": 165,
    "away_id": 168,
    "home_score": 1,
    "away_score": 0,
    "points": 0,
    "is_home": false,
    "corners_for": 0,
    "corners_ag": 0
  },
  {
    "date": "2022-08-13T13:30:00+00:00",
    "season": 2022,
    "home": "Bayer Leverkusen",
    "away": "FC Augsburg",
    "home_id": 168,
    "away_id": 170,
    "home_score": 1,
    "away_score": 2,
    "points": 0,
    "is_home": true,
    "corners_for": 0,
    "corners_ag": 0
  },
  {
    "date": "2022-08-20T13:30:00+00:00",
    "season": 2022,
    "home": "Bayer Leverkusen",
    "away": "1899 Hoffenheim",
    "home_id": 168,
    "away_id": 167,
    "home_score": 0,
    "away_score": 3,
    "points": 0,
    "is_home": true,
    "corners_for": 0,
    "corners_ag": 0
  },
  {
    "date": "2022-08-27T13:30:00+00:00",
    "season": 2022,
    "home": "FSV Mainz 05",
    "away": "Bayer Leverkusen",
    "home_id": 164,
    "away_id": 168,
    "home_score": 0,
    "away_score": 3,
    "points": 3,
    "is_home": false,
    "corners_for": 0,
    "corners_ag": 0
  },
  {
    "date": "2022-09-03T13:30:00+00:00",
    "season": 2022,
    "home": "Bayer Leverkusen",
    "away": "SC Freiburg",
    "home_id": 168,
    "away_id": 160,
    "home_score": 2,
    "away_score": 3,
    "points": 0,
    "is_home": true,
    "corners_for": 0,
    "corners_ag": 0
  },
  {
    "date": "2022-09-07T19:00:00+00:00",
    "season": 2022,
    "home": "Club Brugge KV",
    "away": "Bayer Leverkusen",
    "home_id": 569,
    "away_id": 168,
    "home_score": 1,
    "away_score": 0,
    "points": 0,
    "is_home": false,
    "corners_for": 0,
    "corners_ag": 0
  },
  {
    "date": "2022-09-10T13:30:00+00:00",
    "season": 2022,
    "home": "Hertha Berlin",
    "away": "Bayer Leverkusen",
    "home_id": 159,
    "away_id": 168,
    "home_score": 2,
    "away_score": 2,
    "points": 1,
    "is_home": false,
    "corners_for": 0,
    "corners_ag": 0
  },
  {
    "date": "2022-09-13T19:00:00+00:00",
    "season": 2022,
    "home": "Bayer Leverkusen",
    "away": "Atletico Madrid",
    "home_id": 168,
    "away_id": 530,
    "home_score": 2,
    "away_score": 0,
    "points": 3,
    "is_home": true,
    "corners_for": 0,
    "corners_ag": 0
  },
  {
    "date": "2022-09-17T13:30:00+00:00",
    "season": 2022,
    "home": "Bayer Leverkusen",
    "away": "Werder Bremen",
    "home_id": 168,
    "away_id": 162,
    "home_score": 1,
    "away_score": 1,
    "points": 1,
    "is_home": true,
    "corners_for": 0,
    "corners_ag": 0
  },
  {
    "date": "2022-09-30T18:30:00+00:00",
    "season": 2022,
    "home": "Bayern Munich",
    "away": "Bayer Leverkusen",
    "home_id": 157,
    "away_id": 168,
    "home_score": 4,
    "away_score": 0,
    "points": 0,
    "is_home": false,
    "corners_for": 0,
    "corners_ag": 0
  },
  {
    "date": "2022-10-04T19:00:00+00:00",
    "season": 2022,
    "home": "FC Porto",
    "away": "Bayer Leverkusen",
    "home_id": 212,
    "away_id": 168,
    "home_score": 2,
    "away_score": 0,
    "points": 0,
    "is_home": false,
    "corners_for": 0,
    "corners_ag": 0
  },
  {
    "date": "2022-10-08T13:30:00+00:00",
    "season": 2022,
    "home": "Bayer Leverkusen",
    "away": "FC Schalke 04",
    "home_id": 168,
    "away_id": 174,
    "home_score": 4,
    "away_score": 0,
    "points": 3,
    "is_home": true,
    "corners_for": 0,
    "corners_ag": 0
  },
  {
    "date": "2022-10-12T19:00:00+00:00",
    "season": 2022,
    "home": "Bayer Leverkusen",
    "away": "FC Porto",
    "home_id": 168,
    "away_id": 212,
    "home_score": 0,
    "away_score": 3,
    "points": 0,
    "is_home": true,
    "corners_for": 0,
    "corners_ag": 0
  },
  {
    "date": "2022-10-15T13:30:00+00:00",
    "season": 2022,
    "home": "Eintracht Frankfurt",
    "away": "Bayer Leverkusen",
    "home_id": 169,
    "away_id": 168,
    "home_score": 5,
    "away_score": 1,
    "points": 0,
    "is_home": false,
    "corners_for": 0,
    "corners_ag": 0
  },
  {
    "date": "2022-10-22T13:30:00+00:00",
    "season": 2022,
    "home": "Bayer Leverkusen",
    "away": "VfL Wolfsburg",
    "home_id": 168,
    "away_id": 161,
    "home_score": 2,
    "away_score": 2,
    "points": 1,
    "is_home": true,
    "corners_for": 0,
    "corners_ag": 0
  },
  {
    "date": "2022-10-26T19:00:00+00:00",
    "season": 2022,
    "home": "Atletico Madrid",
    "away": "Bayer Leverkusen",
    "home_id": 530,
    "away_id": 168,
    "home_score": 2,
    "away_score": 2,
    "points": 1,
    "is_home": false,
    "corners_for": 0,
    "corners_ag": 0
  },
  {
    "date": "2022-10-29T13:30:00+00:00",
    "season": 2022,
    "home": "RB Leipzig",
    "away": "Bayer Leverkusen",
    "home_id": 173,
    "away_id": 168,
    "home_score": 2,
    "away_score": 0,
    "points": 0,
    "is_home": false,
    "corners_for": 0,
    "corners_ag": 0
  },
  {
    "date": "2022-11-01T17:45:00+00:00",
    "season": 2022,
    "home": "Bayer Leverkusen",
    "away": "Club Brugge KV",
    "home_id": 168,
    "away_id": 569,
    "home_score": 0,
    "away_score": 0,
    "points": 1,
    "is_home": true,
    "corners_for": 0,
    "corners_ag": 0
  },
  {
    "date": "2022-11-06T14:30:00+00:00",
    "season": 2022,
    "home": "Bayer Leverkusen",
    "away": "Union Berlin",
    "home_id": 168,
    "away_id": 182,
    "home_score": 5,
    "away_score": 0,
    "points": 3,
    "is_home": true,
    "corners_for": 0,
    "corners_ag": 0
  },
  {
    "date": "2022-11-09T17:30:00+00:00",
    "season": 2022,
    "home": "1. FC Köln",
    "away": "Bayer Leverkusen",
    "home_id": 192,
    "away_id": 168,
    "home_score": 1,
    "away_score": 2,
    "points": 3,
    "is_home": false,
    "corners_for": 0,
    "corners_ag": 0
  },
  {
    "date": "2022-11-12T14:30:00+00:00",
    "season": 2022,
    "home": "Bayer Leverkusen",
    "away": "VfB Stuttgart",
    "home_id": 168,
    "away_id": 172,
    "home_score": 2,
    "away_score": 0,
    "points": 3,
    "is_home": true,
    "corners_for": 0,
    "corners_ag": 0
  },
  {
    "date": "2022-11-17T01:00:00+00:00",
    "season": 2022,
    "home": "St. Louis City II",
    "away": "Bayer Leverkusen",
    "home_id": 18740,
    "away_id": 168,
    "home_score": 0,
    "away_score": 3,
    "points": 3,
    "is_home": false,
    "corners_for": 0,
    "corners_ag": 0
  },
  {
    "date": "2022-12-10T13:00:00+00:00",
    "season": 2022,
    "home": "Rangers",
    "away": "Bayer Leverkusen",
    "home_id": 257,
    "away_id": 168,
    "home_score": 3,
    "away_score": 0,
    "points": 0,
    "is_home": false,
    "corners_for": 0,
    "corners_ag": 0
  },
  {
    "date": "2022-12-17T12:00:00+00:00",
    "season": 2022,
    "home": "Bayer Leverkusen",
    "away": "FC Zurich",
    "home_id": 168,
    "away_id": 783,
    "home_score": 4,
    "away_score": 1,
    "points": 3,
    "is_home": true,
    "corners_for": 0,
    "corners_ag": 0
  },
  {
    "date": "2023-01-07T00:00:00+00:00",
    "season": 2023,
    "home": "Bayer Leverkusen",
    "away": "Venezia",
    "home_id": 168,
    "away_id": 517,
    "home_score": 2,
    "away_score": 1,
    "points": 3,
    "is_home": true,
    "corners_for": 0,
    "corners_ag": 0
  },
  {
    "date": "2023-01-15T00:00:00+00:00",
    "season": 2023,
    "home": "Bayer Leverkusen",
    "away": "FC Copenhagen",
    "home_id": 168,
    "away_id": 400,
    "home_score": 1,
    "away_score": 0,
    "points": 3,
    "is_home": true,
    "corners_for": 0,
    "corners_ag": 0
  },
  {
    "date": "2023-01-22T16:30:00+00:00",
    "season": 2022,
    "home": "Borussia Monchengladbach",
    "away": "Bayer Leverkusen",
    "home_id": 163,
    "away_id": 168,
    "home_score": 2,
    "away_score": 3,
    "points": 3,
    "is_home": false,
    "corners_for": 0,
    "corners_ag": 0
  },
  {
    "date": "2023-01-25T19:30:00+00:00",
    "season": 2022,
    "home": "Bayer Leverkusen",
    "away": "Vfl Bochum",
    "home_id": 168,
    "away_id": 176,
    "home_score": 2,
    "away_score": 0,
    "points": 3,
    "is_home": true,
    "corners_for": 0,
    "corners_ag": 0
  },
  {
    "date": "2023-01-29T16:30:00+00:00",
    "season": 2022,
    "home": "Bayer Leverkusen",
    "away": "Borussia Dortmund",
    "home_id": 168,
    "away_id": 165,
    "home_score": 0,
    "away_score": 2,
    "points": 0,
    "is_home": true,
    "corners_for": 0,
    "corners_ag": 0
  },
  {
    "date": "2023-02-03T19:30:00+00:00",
    "season": 2022,
    "home": "FC Augsburg",
    "away": "Bayer Leverkusen",
    "home_id": 170,
    "away_id": 168,
    "home_score": 1,
    "away_score": 0,
    "points": 0,
    "is_home": false,
    "corners_for": 0,
    "corners_ag": 0
  },
  {
    "date": "2023-02-11T14:30:00+00:00",
    "season": 2022,
    "home": "1899 Hoffenheim",
    "away": "Bayer Leverkusen",
    "home_id": 167,
    "away_id": 168,
    "home_score": 1,
    "away_score": 3,
    "points": 3,
    "is_home": false,
    "corners_for": 0,
    "corners_ag": 0
  },
  {
    "date": "2023-02-16T20:00:00+00:00",
    "season": 2022,
    "home": "Bayer Leverkusen",
    "away": "Monaco",
    "home_id": 168,
    "away_id": 91,
    "home_score": 2,
    "away_score": 3,
    "points": 0,
    "is_home": true,
    "corners_for": 0,
    "corners_ag": 0
  },
  {
    "date": "2023-02-19T18:30:00+00:00",
    "season": 2022,
    "home": "Bayer Leverkusen",
    "away": "FSV Mainz 05",
    "home_id": 168,
    "away_id": 164,
    "home_score": 2,
    "away_score": 3,
    "points": 0,
    "is_home": true,
    "corners_for": 0,
    "corners_ag": 0
  },
  {
    "date": "2023-02-26T14:30:00+00:00",
    "season": 2022,
    "home": "SC Freiburg",
    "away": "Bayer Leverkusen",
    "home_id": 160,
    "away_id": 168,
    "home_score": 1,
    "away_score": 1,
    "points": 1,
    "is_home": false,
    "corners_for": 0,
    "corners_ag": 0
  },
  {
    "date": "2023-03-05T14:30:00+00:00",
    "season": 2022,
    "home": "Bayer Leverkusen",
    "away": "Hertha Berlin",
    "home_id": 168,
    "away_id": 159,
    "home_score": 4,
    "away_score": 1,
    "points": 3,
    "is_home": true,
    "corners_for": 0,
    "corners_ag": 0
  },
  {
    "date": "2023-03-09T17:45:00+00:00",
    "season": 2022,
    "home": "Bayer Leverkusen",
    "away": "Ferencvarosi TC",
    "home_id": 168,
    "away_id": 651,
    "home_score": 2,
    "away_score": 0,
    "points": 3,
    "is_home": true,
    "corners_for": 0,
    "corners_ag": 0
  },
  {
    "date": "2023-03-12T16:30:00+00:00",
    "season": 2022,
    "home": "Werder Bremen",
    "away": "Bayer Leverkusen",
    "home_id": 162,
    "away_id": 168,
    "home_score": 2,
    "away_score": 3,
    "points": 3,
    "is_home": false,
    "corners_for": 0,
    "corners_ag": 0
  },
  {
    "date": "2023-03-16T20:00:00+00:00",
    "season": 2022,
    "home": "Ferencvarosi TC",
    "away": "Bayer Leverkusen",
    "home_id": 651,
    "away_id": 168,
    "home_score": 0,
    "away_score": 2,
    "points": 3,
    "is_home": false,
    "corners_for": 0,
    "corners_ag": 0
  },
  {
    "date": "2023-03-19T16:30:00+00:00",
    "season": 2022,
    "home": "Bayer Leverkusen",
    "away": "Bayern Munich",
    "home_id": 168,
    "away_id": 157,
    "home_score": 2,
    "away_score": 1,
    "points": 3,
    "is_home": true,
    "corners_for": 0,
    "corners_ag": 0
  },
  {
    "date": "2023-04-01T13:30:00+00:00",
    "season": 2022,
    "home": "FC Schalke 04",
    "away": "Bayer Leverkusen",
    "home_id": 174,
    "away_id": 168,
    "home_score": 0,
    "away_score": 3,
    "points": 3,
    "is_home": false,
    "corners_for": 0,
    "corners_ag": 0
  },
  {
    "date": "2023-04-08T13:30:00+00:00",
    "season": 2022,
    "home": "Bayer Leverkusen",
    "away": "Eintracht Frankfurt",
    "home_id": 168,
    "away_id": 169,
    "home_score": 3,
    "away_score": 1,
    "points": 3,
    "is_home": true,
    "corners_for": 0,
    "corners_ag": 0
  },
  {
    "date": "2023-04-13T19:00:00+00:00",
    "season": 2022,
    "home": "Bayer Leverkusen",
    "away": "Union St. Gilloise",
    "home_id": 168,
    "away_id": 1393,
    "home_score": 1,
    "away_score": 1,
    "points": 1,
    "is_home": true,
    "corners_for": 0,
    "corners_ag": 0
  },
  {
    "date": "2023-04-16T17:30:00+00:00",
    "season": 2022,
    "home": "VfL Wolfsburg",
    "away": "Bayer Leverkusen",
    "home_id": 161,
    "away_id": 168,
    "home_score": 0,
    "away_score": 0,
    "points": 1,
    "is_home": false,
    "corners_for": 0,
    "corners_ag": 0
  },
  {
    "date": "2023-04-20T19:00:00+00:00",
    "season": 2022,
    "home": "Union St. Gilloise",
    "away": "Bayer Leverkusen",
    "home_id": 1393,
    "away_id": 168,
    "home_score": 1,
    "away_score": 4,
    "points": 3,
    "is_home": false,
    "corners_for": 0,
    "corners_ag": 0
  },
  {
    "date": "2023-04-23T15:30:00+00:00",
    "season": 2022,
    "home": "Bayer Leverkusen",
    "away": "RB Leipzig",
    "home_id": 168,
    "away_id": 173,
    "home_score": 2,
    "away_score": 0,
    "points": 3,
    "is_home": true,
    "corners_for": 0,
    "corners_ag": 0
  },
  {
    "date": "2023-04-29T13:30:00+00:00",
    "season": 2022,
    "home": "Union Berlin",
    "away": "Bayer Leverkusen",
    "home_id": 182,
    "away_id": 168,
    "home_score": 0,
    "away_score": 0,
    "points": 1,
    "is_home": false,
    "corners_for": 0,
    "corners_ag": 0
  },
  {
    "date": "2023-05-05T18:30:00+00:00",
    "season": 2022,
    "home": "Bayer Leverkusen",
    "away": "1. FC Köln",
    "home_id": 168,
    "away_id": 192,
    "home_score": 1,
    "away_score": 2,
    "points": 0,
    "is_home": true,
    "corners_for": 0,
    "corners_ag": 0
  },
  {
    "date": "2023-05-11T19:00:00+00:00",
    "season": 2022,
    "home": "AS Roma",
    "away": "Bayer Leverkusen",
    "home_id": 497,
    "away_id": 168,
    "home_score": 1,
    "away_score": 0,
    "points": 0,
    "is_home": false,
    "corners_for": 0,
    "corners_ag": 0
  },
  {
    "date": "2023-05-14T13:30:00+00:00",
    "season": 2022,
    "home": "VfB Stuttgart",
    "away": "Bayer Leverkusen",
    "home_id": 172,
    "away_id": 168,
    "home_score": 1,
    "away_score": 1,
    "points": 1,
    "is_home": false,
    "corners_for": 0,
    "corners_ag": 0
  },
  {
    "date": "2023-05-18T19:00:00+00:00",
    "season": 2022,
    "home": "Bayer Leverkusen",
    "away": "AS Roma",
    "home_id": 168,
    "away_id": 497,
    "home_score": 0,
    "away_score": 0,
    "points": 1,
    "is_home": true,
    "corners_for": 0,
    "corners_ag": 0
  },
  {
    "date": "2023-05-21T17:30:00+00:00",
    "season": 2022,
    "home": "Bayer Leverkusen",
    "away": "Borussia Monchengladbach",
    "home_id": 168,
    "away_id": 163,
    "home_score": 2,
    "away_score": 2,
    "points": 1,
    "is_home": true,
    "corners_for": 0,
    "corners_ag": 0
  },
  {
    "date": "2023-05-27T13:30:00+00:00",
    "season": 2022,
    "home": "Vfl Bochum",
    "away": "Bayer Leverkusen",
    "home_id": 176,
    "away_id": 168,
    "home_score": 3,
    "away_score": 0,
    "points": 0,
    "is_home": false,
    "corners_for": 0,
    "corners_ag": 0
  },
  {
    "date": "2023-07-21T15:30:00+00:00",
    "season": 2023,
    "home": "Bayer Leverkusen",
    "away": "SC Paderborn 07",
    "home_id": 168,
    "away_id": 185,
    "home_score": 1,
    "away_score": 2,
    "points": 0,
    "is_home": true,
    "corners_for": 0,
    "corners_ag": 0
  },
  {
    "date": "2023-07-29T16:00:00+00:00",
    "season": 2023,
    "home": "Real Sociedad",
    "away": "Bayer Leverkusen",
    "home_id": 548,
    "away_id": 168,
    "home_score": 1,
    "away_score": 0,
    "points": 0,
    "is_home": false,
    "corners_for": 0,
    "corners_ag": 0
  },
  {
    "date": "2023-08-02T18:45:00+00:00",
    "season": 2023,
    "home": "Marseille",
    "away": "Bayer Leverkusen",
    "home_id": 81,
    "away_id": 168,
    "home_score": 1,
    "away_score": 2,
    "points": 3,
    "is_home": false,
    "corners_for": 0,
    "corners_ag": 0
  },
  {
    "date": "2023-08-05T11:30:00+00:00",
    "season": 2023,
    "home": "Bayer Leverkusen",
    "away": "West Ham",
    "home_id": 168,
    "away_id": 48,
    "home_score": 4,
    "away_score": 0,
    "points": 3,
    "is_home": true,
    "corners_for": 0,
    "corners_ag": 0
  },
  {
    "date": "2023-08-12T13:30:00+00:00",
    "season": 2023,
    "home": "Teutonia Ottensen",
    "away": "Bayer Leverkusen",
    "home_id": 12878,
    "away_id": 168,
    "home_score": 0,
    "away_score": 8,
    "points": 3,
    "is_home": false,
    "corners_for": 0,
    "corners_ag": 0
  },
  {
    "date": "2023-08-19T13:30:00+00:00",
    "season": 2023,
    "home": "Bayer Leverkusen",
    "away": "RB Leipzig",
    "home_id": 168,
    "away_id": 173,
    "home_score": 3,
    "away_score": 2,
    "points": 3,
    "is_home": true,
    "corners_for": 0,
    "corners_ag": 0
  },
  {
    "date": "2023-08-26T16:30:00+00:00",
    "season": 2023,
    "home": "Borussia Monchengladbach",
    "away": "Bayer Leverkusen",
    "home_id": 163,
    "away_id": 168,
    "home_score": 0,
    "away_score": 3,
    "points": 3,
    "is_home": false,
    "corners_for": 0,
    "corners_ag": 0
  },
  {
    "date": "2023-09-02T13:30:00+00:00",
    "season": 2023,
    "home": "Bayer Leverkusen",
    "away": "SV Darmstadt 98",
    "home_id": 168,
    "away_id": 181,
    "home_score": 5,
    "away_score": 1,
    "points": 3,
    "is_home": true,
    "corners_for": 0,
    "corners_ag": 0
  },
  {
    "date": "2023-09-07T09:00:00+00:00",
    "season": 2023,
    "home": "Bayer Leverkusen",
    "away": "Alemannia Aachen",
    "home_id": 168,
    "away_id": 4259,
    "home_score": 4,
    "away_score": 2,
    "points": 3,
    "is_home": true,
    "corners_for": 0,
    "corners_ag": 0
  },
  {
    "date": "2023-09-15T18:30:00+00:00",
    "season": 2023,
    "home": "Bayern Munich",
    "away": "Bayer Leverkusen",
    "home_id": 157,
    "away_id": 168,
    "home_score": 2,
    "away_score": 2,
    "points": 1,
    "is_home": false,
    "corners_for": 0,
    "corners_ag": 0
  },
  {
    "date": "2023-09-21T16:45:00+00:00",
    "season": 2023,
    "home": "Bayer Leverkusen",
    "away": "BK Hacken",
    "home_id": 168,
    "away_id": 367,
    "home_score": 4,
    "away_score": 0,
    "points": 3,
    "is_home": true,
    "corners_for": 0,
    "corners_ag": 0
  },
  {
    "date": "2023-09-24T13:30:00+00:00",
    "season": 2023,
    "home": "Bayer Leverkusen",
    "away": "FC Heidenheim",
    "home_id": 168,
    "away_id": 180,
    "home_score": 4,
    "away_score": 1,
    "points": 3,
    "is_home": true,
    "corners_for": 0,
    "corners_ag": 0
  },
  {
    "date": "2023-09-30T13:30:00+00:00",
    "season": 2023,
    "home": "FSV Mainz 05",
    "away": "Bayer Leverkusen",
    "home_id": 164,
    "away_id": 168,
    "home_score": 0,
    "away_score": 3,
    "points": 3,
    "is_home": false,
    "corners_for": 0,
    "corners_ag": 0
  },
  {
    "date": "2023-10-05T19:00:00+00:00",
    "season": 2023,
    "home": "Molde",
    "away": "Bayer Leverkusen",
    "home_id": 329,
    "away_id": 168,
    "home_score": 1,
    "away_score": 2,
    "points": 3,
    "is_home": false,
    "corners_for": 0,
    "corners_ag": 0
  },
  {
    "date": "2023-10-08T13:30:00+00:00",
    "season": 2023,
    "home": "Bayer Leverkusen",
    "away": "1. FC Köln",
    "home_id": 168,
    "away_id": 192,
    "home_score": 3,
    "away_score": 0,
    "points": 3,
    "is_home": true,
    "corners_for": 0,
    "corners_ag": 0
  },
  {
    "date": "2023-10-21T13:30:00+00:00",
    "season": 2023,
    "home": "VfL Wolfsburg",
    "away": "Bayer Leverkusen",
    "home_id": 161,
    "away_id": 168,
    "home_score": 1,
    "away_score": 2,
    "points": 3,
    "is_home": false,
    "corners_for": 0,
    "corners_ag": 0
  },
  {
    "date": "2023-10-26T19:00:00+00:00",
    "season": 2023,
    "home": "Bayer Leverkusen",
    "away": "Qarabag",
    "home_id": 168,
    "away_id": 556,
    "home_score": 5,
    "away_score": 1,
    "points": 3,
    "is_home": true,
    "corners_for": 0,
    "corners_ag": 0
  },
  {
    "date": "2023-10-29T16:30:00+00:00",
    "season": 2023,
    "home": "Bayer Leverkusen",
    "away": "SC Freiburg",
    "home_id": 168,
    "away_id": 160,
    "home_score": 2,
    "away_score": 1,
    "points": 3,
    "is_home": true,
    "corners_for": 0,
    "corners_ag": 0
  },
  {
    "date": "2023-11-01T17:00:00+00:00",
    "season": 2023,
    "home": "SV Sandhausen",
    "away": "Bayer Leverkusen",
    "home_id": 189,
    "away_id": 168,
    "home_score": 2,
    "away_score": 5,
    "points": 3,
    "is_home": false,
    "corners_for": 0,
    "corners_ag": 0
  },
  {
    "date": "2023-11-04T14:30:00+00:00",
    "season": 2023,
    "home": "1899 Hoffenheim",
    "away": "Bayer Leverkusen",
    "home_id": 167,
    "away_id": 168,
    "home_score": 2,
    "away_score": 3,
    "points": 3,
    "is_home": false,
    "corners_for": 0,
    "corners_ag": 0
  },
  {
    "date": "2023-11-09T17:45:00+00:00",
    "season": 2023,
    "home": "Qarabag",
    "away": "Bayer Leverkusen",
    "home_id": 556,
    "away_id": 168,
    "home_score": 0,
    "away_score": 1,
    "points": 3,
    "is_home": false,
    "corners_for": 0,
    "corners_ag": 0
  },
  {
    "date": "2023-11-12T14:30:00+00:00",
    "season": 2023,
    "home": "Bayer Leverkusen",
    "away": "Union Berlin",
    "home_id": 168,
    "away_id": 182,
    "home_score": 4,
    "away_score": 0,
    "points": 3,
    "is_home": true,
    "corners_for": 0,
    "corners_ag": 0
  },
  {
    "date": "2023-11-25T14:30:00+00:00",
    "season": 2023,
    "home": "Werder Bremen",
    "away": "Bayer Leverkusen",
    "home_id": 162,
    "away_id": 168,
    "home_score": 0,
    "away_score": 3,
    "points": 3,
    "is_home": false,
    "corners_for": 0,
    "corners_ag": 0
  },
  {
    "date": "2023-11-30T20:00:00+00:00",
    "season": 2023,
    "home": "BK Hacken",
    "away": "Bayer Leverkusen",
    "home_id": 367,
    "away_id": 168,
    "home_score": 0,
    "away_score": 2,
    "points": 3,
    "is_home": false,
    "corners_for": 0,
    "corners_ag": 0
  },
  {
    "date": "2023-12-03T16:30:00+00:00",
    "season": 2023,
    "home": "Bayer Leverkusen",
    "away": "Borussia Dortmund",
    "home_id": 168,
    "away_id": 165,
    "home_score": 1,
    "away_score": 1,
    "points": 1,
    "is_home": true,
    "corners_for": 0,
    "corners_ag": 0
  },
  {
    "date": "2023-12-06T17:00:00+00:00",
    "season": 2023,
    "home": "Bayer Leverkusen",
    "away": "SC Paderborn 07",
    "home_id": 168,
    "away_id": 185,
    "home_score": 3,
    "away_score": 1,
    "points": 3,
    "is_home": true,
    "corners_for": 0,
    "corners_ag": 0
  },
  {
    "date": "2023-12-10T14:30:00+00:00",
    "season": 2023,
    "home": "VfB Stuttgart",
    "away": "Bayer Leverkusen",
    "home_id": 172,
    "away_id": 168,
    "home_score": 1,
    "away_score": 1,
    "points": 1,
    "is_home": false,
    "corners_for": 0,
    "corners_ag": 0
  },
  {
    "date": "2023-12-14T17:45:00+00:00",
    "season": 2023,
    "home": "Bayer Leverkusen",
    "away": "Molde",
    "home_id": 168,
    "away_id": 329,
    "home_score": 5,
    "away_score": 1,
    "points": 3,
    "is_home": true,
    "corners_for": 0,
    "corners_ag": 0
  },
  {
    "date": "2023-12-17T16:30:00+00:00",
    "season": 2023,
    "home": "Bayer Leverkusen",
    "away": "Eintracht Frankfurt",
    "home_id": 168,
    "away_id": 169,
    "home_score": 3,
    "away_score": 0,
    "points": 3,
    "is_home": true,
    "corners_for": 0,
    "corners_ag": 0
  },
  {
    "date": "2023-12-20T19:30:00+00:00",
    "season": 2023,
    "home": "Bayer Leverkusen",
    "away": "Vfl Bochum",
    "home_id": 168,
    "away_id": 176,
    "home_score": 4,
    "away_score": 0,
    "points": 3,
    "is_home": true,
    "corners_for": 0,
    "corners_ag": 0
  },
  {
    "date": "2024-01-07T14:00:00+00:00",
    "season": 2024,
    "home": "Bayer Leverkusen",
    "away": "Venezia",
    "home_id": 168,
    "away_id": 517,
    "home_score": 4,
    "away_score": 1,
    "points": 3,
    "is_home": true,
    "corners_for": 0,
    "corners_ag": 0
  },
  {
    "date": "2024-01-13T14:30:00+00:00",
    "season": 2023,
    "home": "FC Augsburg",
    "away": "Bayer Leverkusen",
    "home_id": 170,
    "away_id": 168,
    "home_score": 0,
    "away_score": 1,
    "points": 3,
    "is_home": false,
    "corners_for": 0,
    "corners_ag": 0
  },
  {
    "date": "2024-01-20T17:30:00+00:00",
    "season": 2023,
    "home": "RB Leipzig",
    "away": "Bayer Leverkusen",
    "home_id": 173,
    "away_id": 168,
    "home_score": 2,
    "away_score": 3,
    "points": 3,
    "is_home": false,
    "corners_for": 0,
    "corners_ag": 0
  },
  {
    "date": "2024-01-27T17:30:00+00:00",
    "season": 2023,
    "home": "Bayer Leverkusen",
    "away": "Borussia Monchengladbach",
    "home_id": 168,
    "away_id": 163,
    "home_score": 0,
    "away_score": 0,
    "points": 1,
    "is_home": true,
    "corners_for": 0,
    "corners_ag": 0
  },
  {
    "date": "2024-02-03T14:30:00+00:00",
    "season": 2023,
    "home": "SV Darmstadt 98",
    "away": "Bayer Leverkusen",
    "home_id": 181,
    "away_id": 168,
    "home_score": 0,
    "away_score": 2,
    "points": 3,
    "is_home": false,
    "corners_for": 0,
    "corners_ag": 0
  },
  {
    "date": "2024-02-06T19:45:00+00:00",
    "season": 2023,
    "home": "Bayer Leverkusen",
    "away": "VfB Stuttgart",
    "home_id": 168,
    "away_id": 172,
    "home_score": 3,
    "away_score": 2,
    "points": 3,
    "is_home": true,
    "corners_for": 0,
    "corners_ag": 0
  },
  {
    "date": "2024-02-10T17:30:00+00:00",
    "season": 2023,
    "home": "Bayer Leverkusen",
    "away": "Bayern Munich",
    "home_id": 168,
    "away_id": 157,
    "home_score": 3,
    "away_score": 0,
    "points": 3,
    "is_home": true,
    "corners_for": 0,
    "corners_ag": 0
  },
  {
    "date": "2024-02-17T14:30:00+00:00",
    "season": 2023,
    "home": "FC Heidenheim",
    "away": "Bayer Leverkusen",
    "home_id": 180,
    "away_id": 168,
    "home_score": 1,
    "away_score": 2,
    "points": 3,
    "is_home": false,
    "corners_for": 0,
    "corners_ag": 0
  },
  {
    "date": "2024-02-23T19:30:00+00:00",
    "season": 2023,
    "home": "Bayer Leverkusen",
    "away": "FSV Mainz 05",
    "home_id": 168,
    "away_id": 164,
    "home_score": 2,
    "away_score": 1,
    "points": 3,
    "is_home": true,
    "corners_for": 0,
    "corners_ag": 0
  },
  {
    "date": "2024-03-03T14:30:00+00:00",
    "season": 2023,
    "home": "1. FC Köln",
    "away": "Bayer Leverkusen",
    "home_id": 192,
    "away_id": 168,
    "home_score": 0,
    "away_score": 2,
    "points": 3,
    "is_home": false,
    "corners_for": 0,
    "corners_ag": 0
  },
  {
    "date": "2024-03-07T17:45:00+00:00",
    "season": 2023,
    "home": "Qarabag",
    "away": "Bayer Leverkusen",
    "home_id": 556,
    "away_id": 168,
    "home_score": 2,
    "away_score": 2,
    "points": 1,
    "is_home": false,
    "corners_for": 0,
    "corners_ag": 0
  },
  {
    "date": "2024-03-10T18:30:00+00:00",
    "season": 2023,
    "home": "Bayer Leverkusen",
    "away": "VfL Wolfsburg",
    "home_id": 168,
    "away_id": 161,
    "home_score": 2,
    "away_score": 0,
    "points": 3,
    "is_home": true,
    "corners_for": 0,
    "corners_ag": 0
  },
  {
    "date": "2024-03-14T20:00:00+00:00",
    "season": 2023,
    "home": "Bayer Leverkusen",
    "away": "Qarabag",
    "home_id": 168,
    "away_id": 556,
    "home_score": 3,
    "away_score": 2,
    "points": 3,
    "is_home": true,
    "corners_for": 0,
    "corners_ag": 0
  },
  {
    "date": "2024-03-17T14:30:00+00:00",
    "season": 2023,
    "home": "SC Freiburg",
    "away": "Bayer Leverkusen",
    "home_id": 160,
    "away_id": 168,
    "home_score": 2,
    "away_score": 3,
    "points": 3,
    "is_home": false,
    "corners_for": 0,
    "corners_ag": 0
  },
  {
    "date": "2024-03-30T14:30:00+00:00",
    "season": 2023,
    "home": "Bayer Leverkusen",
    "away": "1899 Hoffenheim",
    "home_id": 168,
    "away_id": 167,
    "home_score": 2,
    "away_score": 1,
    "points": 3,
    "is_home": true,
    "corners_for": 0,
    "corners_ag": 0
  },
  {
    "date": "2024-04-03T18:45:00+00:00",
    "season": 2023,
    "home": "Bayer Leverkusen",
    "away": "Fortuna Dusseldorf",
    "home_id": 168,
    "away_id": 158,
    "home_score": 4,
    "away_score": 0,
    "points": 3,
    "is_home": true,
    "corners_for": 0,
    "corners_ag": 0
  },
  {
    "date": "2024-04-06T13:30:00+00:00",
    "season": 2023,
    "home": "Union Berlin",
    "away": "Bayer Leverkusen",
    "home_id": 182,
    "away_id": 168,
    "home_score": 0,
    "away_score": 1,
    "points": 3,
    "is_home": false,
    "corners_for": 0,
    "corners_ag": 0
  },
  {
    "date": "2024-04-11T19:00:00+00:00",
    "season": 2023,
    "home": "Bayer Leverkusen",
    "away": "West Ham",
    "home_id": 168,
    "away_id": 48,
    "home_score": 2,
    "away_score": 0,
    "points": 3,
    "is_home": true,
    "corners_for": 0,
    "corners_ag": 0
  },
  {
    "date": "2024-04-14T15:30:00+00:00",
    "season": 2023,
    "home": "Bayer Leverkusen",
    "away": "Werder Bremen",
    "home_id": 168,
    "away_id": 162,
    "home_score": 5,
    "away_score": 0,
    "points": 3,
    "is_home": true,
    "corners_for": 0,
    "corners_ag": 0
  },
  {
    "date": "2024-04-18T19:00:00+00:00",
    "season": 2023,
    "home": "West Ham",
    "away": "Bayer Leverkusen",
    "home_id": 48,
    "away_id": 168,
    "home_score": 1,
    "away_score": 1,
    "points": 1,
    "is_home": false,
    "corners_for": 0,
    "corners_ag": 0
  },
  {
    "date": "2024-04-21T15:30:00+00:00",
    "season": 2023,
    "home": "Borussia Dortmund",
    "away": "Bayer Leverkusen",
    "home_id": 165,
    "away_id": 168,
    "home_score": 1,
    "away_score": 1,
    "points": 1,
    "is_home": false,
    "corners_for": 0,
    "corners_ag": 0
  },
  {
    "date": "2024-04-27T16:30:00+00:00",
    "season": 2023,
    "home": "Bayer Leverkusen",
    "away": "VfB Stuttgart",
    "home_id": 168,
    "away_id": 172,
    "home_score": 2,
    "away_score": 2,
    "points": 1,
    "is_home": true,
    "corners_for": 0,
    "corners_ag": 0
  },
  {
    "date": "2024-05-02T19:00:00+00:00",
    "season": 2023,
    "home": "AS Roma",
    "away": "Bayer Leverkusen",
    "home_id": 497,
    "away_id": 168,
    "home_score": 0,
    "away_score": 2,
    "points": 3,
    "is_home": false,
    "corners_for": 0,
    "corners_ag": 0
  },
  {
    "date": "2024-05-05T15:30:00+00:00",
    "season": 2023,
    "home": "Eintracht Frankfurt",
    "away": "Bayer Leverkusen",
    "home_id": 169,
    "away_id": 168,
    "home_score": 1,
    "away_score": 5,
    "points": 3,
    "is_home": false,
    "corners_for": 0,
    "corners_ag": 0
  },
  {
    "date": "2024-05-09T19:00:00+00:00",
    "season": 2023,
    "home": "Bayer Leverkusen",
    "away": "AS Roma",
    "home_id": 168,
    "away_id": 497,
    "home_score": 2,
    "away_score": 2,
    "points": 1,
    "is_home": true,
    "corners_for": 0,
    "corners_ag": 0
  },
  {
    "date": "2024-05-12T17:30:00+00:00",
    "season": 2023,
    "home": "Vfl Bochum",
    "away": "Bayer Leverkusen",
    "home_id": 176,
    "away_id": 168,
    "home_score": 0,
    "away_score": 5,
    "points": 3,
    "is_home": false,
    "corners_for": 0,
    "corners_ag": 0
  },
  {
    "date": "2024-05-18T13:30:00+00:00",
    "season": 2023,
    "home": "Bayer Leverkusen",
    "away": "FC Augsburg",
    "home_id": 168,
    "away_id": 170,
    "home_score": 2,
    "away_score": 1,
    "points": 3,
    "is_home": true,
    "corners_for": 0,
    "corners_ag": 0
  },
  {
    "date": "2024-05-22T19:00:00+00:00",
    "season": 2023,
    "home": "Atalanta",
    "away": "Bayer Leverkusen",
    "home_id": 499,
    "away_id": 168,
    "home_score": 3,
    "away_score": 0,
    "points": 0,
    "is_home": false,
    "corners_for": 0,
    "corners_ag": 0
  },
  {
    "date": "2024-05-25T18:00:00+00:00",
    "season": 2023,
    "home": "FC Kaiserslautern",
    "away": "Bayer Leverkusen",
    "home_id": 745,
    "away_id": 168,
    "home_score": 0,
    "away_score": 1,
    "points": 3,
    "is_home": false,
    "corners_for": 0,
    "corners_ag": 0
  },
  {
    "date": "2024-07-26T17:00:00+00:00",
    "season": 2024,
    "home": "Rot-Weiß Essen",
    "away": "Bayer Leverkusen",
    "home_id": 1621,
    "away_id": 168,
    "home_score": 1,
    "away_score": 2,
    "points": 3,
    "is_home": false,
    "corners_for": 0,
    "corners_ag": 0
  },
  {
    "date": "2024-08-03T14:00:00+00:00",
    "season": 2024,
    "home": "Lens",
    "away": "Bayer Leverkusen",
    "home_id": 116,
    "away_id": 168,
    "home_score": 2,
    "away_score": 2,
    "points": 1,
    "is_home": false,
    "corners_for": 0,
    "corners_ag": 0
  },
  {
    "date": "2024-08-07T17:00:00+00:00",
    "season": 2024,
    "home": "Arsenal",
    "away": "Bayer Leverkusen",
    "home_id": 42,
    "away_id": 168,
    "home_score": 4,
    "away_score": 1,
    "points": 0,
    "is_home": false,
    "corners_for": 0,
    "corners_ag": 0
  },
  {
    "date": "2024-08-10T13:30:00+00:00",
    "season": 2024,
    "home": "Bayer Leverkusen",
    "away": "Real Betis",
    "home_id": 168,
    "away_id": 543,
    "home_score": 1,
    "away_score": 1,
    "points": 1,
    "is_home": true,
    "corners_for": 0,
    "corners_ag": 0
  },
  {
    "date": "2024-08-23T18:30:00+00:00",
    "season": 2024,
    "home": "Borussia Mönchengladbach",
    "away": "Bayer Leverkusen",
    "home_id": 163,
    "away_id": 168,
    "home_score": 2,
    "away_score": 3,
    "points": 3,
    "is_home": false,
    "corners_for": 0,
    "corners_ag": 0
  },
  {
    "date": "2024-08-28T16:00:00+00:00",
    "season": 2024,
    "home": "FC Carl Zeiss Jena",
    "away": "Bayer Leverkusen",
    "home_id": 1325,
    "away_id": 168,
    "home_score": 0,
    "away_score": 1,
    "points": 3,
    "is_home": false,
    "corners_for": 0,
    "corners_ag": 0
  },
  {
    "date": "2024-08-31T16:30:00+00:00",
    "season": 2024,
    "home": "Bayer Leverkusen",
    "away": "RB Leipzig",
    "home_id": 168,
    "away_id": 173,
    "home_score": 2,
    "away_score": 3,
    "points": 0,
    "is_home": true,
    "corners_for": 0,
    "corners_ag": 0
  },
  {
    "date": "2024-09-14T13:30:00+00:00",
    "season": 2024,
    "home": "1899 Hoffenheim",
    "away": "Bayer Leverkusen",
    "home_id": 167,
    "away_id": 168,
    "home_score": 1,
    "away_score": 4,
    "points": 3,
    "is_home": false,
    "corners_for": 0,
    "corners_ag": 0
  },
  {
    "date": "2024-09-19T16:45:00+00:00",
    "season": 2024,
    "home": "Feyenoord",
    "away": "Bayer Leverkusen",
    "home_id": 209,
    "away_id": 168,
    "home_score": 0,
    "away_score": 4,
    "points": 3,
    "is_home": false,
    "corners_for": 0,
    "corners_ag": 0
  },
  {
    "date": "2024-09-22T13:30:00+00:00",
    "season": 2024,
    "home": "Bayer Leverkusen",
    "away": "VfL Wolfsburg",
    "home_id": 168,
    "away_id": 161,
    "home_score": 4,
    "away_score": 3,
    "points": 3,
    "is_home": true,
    "corners_for": 0,
    "corners_ag": 0
  },
  {
    "date": "2024-09-28T16:30:00+00:00",
    "season": 2024,
    "home": "Bayern München",
    "away": "Bayer Leverkusen",
    "home_id": 157,
    "away_id": 168,
    "home_score": 1,
    "away_score": 1,
    "points": 1,
    "is_home": false,
    "corners_for": 0,
    "corners_ag": 0
  },
  {
    "date": "2024-10-01T19:00:00+00:00",
    "season": 2024,
    "home": "Bayer Leverkusen",
    "away": "AC Milan",
    "home_id": 168,
    "away_id": 489,
    "home_score": 1,
    "away_score": 0,
    "points": 3,
    "is_home": true,
    "corners_for": 0,
    "corners_ag": 0
  },
  {
    "date": "2024-10-05T13:30:00+00:00",
    "season": 2024,
    "home": "Bayer Leverkusen",
    "away": "Holstein Kiel",
    "home_id": 168,
    "away_id": 191,
    "home_score": 2,
    "away_score": 2,
    "points": 1,
    "is_home": true,
    "corners_for": 0,
    "corners_ag": 0
  },
  {
    "date": "2024-10-19T13:30:00+00:00",
    "season": 2024,
    "home": "Bayer Leverkusen",
    "away": "Eintracht Frankfurt",
    "home_id": 168,
    "away_id": 169,
    "home_score": 2,
    "away_score": 1,
    "points": 3,
    "is_home": true,
    "corners_for": 0,
    "corners_ag": 0
  },
  {
    "date": "2024-10-23T16:45:00+00:00",
    "season": 2024,
    "home": "Stade Brestois 29",
    "away": "Bayer Leverkusen",
    "home_id": 106,
    "away_id": 168,
    "home_score": 1,
    "away_score": 1,
    "points": 1,
    "is_home": false,
    "corners_for": 0,
    "corners_ag": 0
  },
  {
    "date": "2024-10-26T16:30:00+00:00",
    "season": 2024,
    "home": "Werder Bremen",
    "away": "Bayer Leverkusen",
    "home_id": 162,
    "away_id": 168,
    "home_score": 2,
    "away_score": 2,
    "points": 1,
    "is_home": false,
    "corners_for": 0,
    "corners_ag": 0
  },
  {
    "date": "2024-10-29T17:00:00+00:00",
    "season": 2024,
    "home": "Bayer Leverkusen",
    "away": "SV Elversberg",
    "home_id": 168,
    "away_id": 1660,
    "home_score": 3,
    "away_score": 0,
    "points": 3,
    "is_home": true,
    "corners_for": 0,
    "corners_ag": 0
  },
  {
    "date": "2024-11-01T19:30:00+00:00",
    "season": 2024,
    "home": "Bayer Leverkusen",
    "away": "VfB Stuttgart",
    "home_id": 168,
    "away_id": 172,
    "home_score": 0,
    "away_score": 0,
    "points": 1,
    "is_home": true,
    "corners_for": 0,
    "corners_ag": 0
  },
  {
    "date": "2024-11-05T20:00:00+00:00",
    "season": 2024,
    "home": "Liverpool",
    "away": "Bayer Leverkusen",
    "home_id": 40,
    "away_id": 168,
    "home_score": 4,
    "away_score": 0,
    "points": 0,
    "is_home": false,
    "corners_for": 0,
    "corners_ag": 0
  },
  {
    "date": "2024-11-09T14:30:00+00:00",
    "season": 2024,
    "home": "VfL Bochum",
    "away": "Bayer Leverkusen",
    "home_id": 176,
    "away_id": 168,
    "home_score": 1,
    "away_score": 1,
    "points": 1,
    "is_home": false,
    "corners_for": 0,
    "corners_ag": 0
  },
  {
    "date": "2024-11-23T14:30:00+00:00",
    "season": 2024,
    "home": "Bayer Leverkusen",
    "away": "1. FC Heidenheim",
    "home_id": 168,
    "away_id": 180,
    "home_score": 5,
    "away_score": 2,
    "points": 3,
    "is_home": true,
    "corners_for": 0,
    "corners_ag": 0
  },
  {
    "date": "2024-11-26T20:00:00+00:00",
    "season": 2024,
    "home": "Bayer Leverkusen",
    "away": "Red Bull Salzburg",
    "home_id": 168,
    "away_id": 571,
    "home_score": 5,
    "away_score": 0,
    "points": 3,
    "is_home": true,
    "corners_for": 0,
    "corners_ag": 0
  },
  {
    "date": "2024-11-30T14:30:00+00:00",
    "season": 2024,
    "home": "Union Berlin",
    "away": "Bayer Leverkusen",
    "home_id": 182,
    "away_id": 168,
    "home_score": 1,
    "away_score": 2,
    "points": 3,
    "is_home": false,
    "corners_for": 0,
    "corners_ag": 0
  },
  {
    "date": "2024-12-03T19:45:00+00:00",
    "season": 2024,
    "home": "Bayern München",
    "away": "Bayer Leverkusen",
    "home_id": 157,
    "away_id": 168,
    "home_score": 0,
    "away_score": 1,
    "points": 3,
    "is_home": false,
    "corners_for": 0,
    "corners_ag": 0
  },
  {
    "date": "2024-12-07T14:30:00+00:00",
    "season": 2024,
    "home": "Bayer Leverkusen",
    "away": "FC St. Pauli",
    "home_id": 168,
    "away_id": 186,
    "home_score": 2,
    "away_score": 1,
    "points": 3,
    "is_home": true,
    "corners_for": 0,
    "corners_ag": 0
  },
  {
    "date": "2024-12-10T20:00:00+00:00",
    "season": 2024,
    "home": "Bayer Leverkusen",
    "away": "Inter",
    "home_id": 168,
    "away_id": 505,
    "home_score": 1,
    "away_score": 0,
    "points": 3,
    "is_home": true,
    "corners_for": 0,
    "corners_ag": 0
  },
  {
    "date": "2024-12-14T14:30:00+00:00",
    "season": 2024,
    "home": "FC Augsburg",
    "away": "Bayer Leverkusen",
    "home_id": 170,
    "away_id": 168,
    "home_score": 0,
    "away_score": 2,
    "points": 3,
    "is_home": false,
    "corners_for": 0,
    "corners_ag": 0
  },
  {
    "date": "2024-12-21T17:30:00+00:00",
    "season": 2024,
    "home": "Bayer Leverkusen",
    "away": "SC Freiburg",
    "home_id": 168,
    "away_id": 160,
    "home_score": 5,
    "away_score": 1,
    "points": 3,
    "is_home": true,
    "corners_for": 0,
    "corners_ag": 0
  },
  {
    "date": "2025-01-05T11:00:00+00:00",
    "season": 2025,
    "home": "Bayer Leverkusen",
    "away": "Rot-weiss Oberhausen",
    "home_id": 168,
    "away_id": 1658,
    "home_score": 2,
    "away_score": 0,
    "points": 3,
    "is_home": true,
    "corners_for": 0,
    "corners_ag": 0
  },
  {
    "date": "2025-01-10T19:45:00+00:00",
    "season": 2024,
    "home": "Borussia Dortmund",
    "away": "Bayer Leverkusen",
    "home_id": 165,
    "away_id": 168,
    "home_score": 2,
    "away_score": 3,
    "points": 3,
    "is_home": false,
    "corners_for": 0,
    "corners_ag": 0
  },
  {
    "date": "2025-01-14T19:30:00+00:00",
    "season": 2024,
    "home": "Bayer Leverkusen",
    "away": "FSV Mainz 05",
    "home_id": 168,
    "away_id": 164,
    "home_score": 1,
    "away_score": 0,
    "points": 3,
    "is_home": true,
    "corners_for": 0,
    "corners_ag": 0
  },
  {
    "date": "2025-01-18T17:30:00+00:00",
    "season": 2024,
    "home": "Bayer Leverkusen",
    "away": "Borussia Mönchengladbach",
    "home_id": 168,
    "away_id": 163,
    "home_score": 3,
    "away_score": 1,
    "points": 3,
    "is_home": true,
    "corners_for": 0,
    "corners_ag": 0
  },
  {
    "date": "2025-01-21T20:00:00+00:00",
    "season": 2024,
    "home": "Atletico Madrid",
    "away": "Bayer Leverkusen",
    "home_id": 530,
    "away_id": 168,
    "home_score": 2,
    "away_score": 1,
    "points": 0,
    "is_home": false,
    "corners_for": 0,
    "corners_ag": 0
  },
  {
    "date": "2025-01-25T14:30:00+00:00",
    "season": 2024,
    "home": "RB Leipzig",
    "away": "Bayer Leverkusen",
    "home_id": 173,
    "away_id": 168,
    "home_score": 2,
    "away_score": 2,
    "points": 1,
    "is_home": false,
    "corners_for": 0,
    "corners_ag": 0
  },
  {
    "date": "2025-01-29T20:00:00+00:00",
    "season": 2024,
    "home": "Bayer Leverkusen",
    "away": "Sparta Praha",
    "home_id": 168,
    "away_id": 628,
    "home_score": 2,
    "away_score": 0,
    "points": 3,
    "is_home": true,
    "corners_for": 0,
    "corners_ag": 0
  },
  {
    "date": "2025-02-02T16:30:00+00:00",
    "season": 2024,
    "home": "Bayer Leverkusen",
    "away": "1899 Hoffenheim",
    "home_id": 168,
    "away_id": 167,
    "home_score": 3,
    "away_score": 1,
    "points": 3,
    "is_home": true,
    "corners_for": 0,
    "corners_ag": 0
  },
  {
    "date": "2025-02-08T14:30:00+00:00",
    "season": 2024,
    "home": "VfL Wolfsburg",
    "away": "Bayer Leverkusen",
    "home_id": 161,
    "away_id": 168,
    "home_score": 0,
    "away_score": 0,
    "points": 1,
    "is_home": false,
    "corners_for": 0,
    "corners_ag": 0
  },
  {
    "date": "2025-02-15T17:30:00+00:00",
    "season": 2024,
    "home": "Bayer Leverkusen",
    "away": "Bayern München",
    "home_id": 168,
    "away_id": 157,
    "home_score": 0,
    "away_score": 0,
    "points": 1,
    "is_home": true,
    "corners_for": 0,
    "corners_ag": 0
  },
  {
    "date": "2025-02-22T14:30:00+00:00",
    "season": 2024,
    "home": "Holstein Kiel",
    "away": "Bayer Leverkusen",
    "home_id": 191,
    "away_id": 168,
    "home_score": 0,
    "away_score": 2,
    "points": 3,
    "is_home": false,
    "corners_for": 0,
    "corners_ag": 0
  },
  {
    "date": "2025-03-01T17:30:00+00:00",
    "season": 2024,
    "home": "Eintracht Frankfurt",
    "away": "Bayer Leverkusen",
    "home_id": 169,
    "away_id": 168,
    "home_score": 1,
    "away_score": 4,
    "points": 3,
    "is_home": false,
    "corners_for": 0,
    "corners_ag": 0
  },
  {
    "date": "2025-03-05T20:00:00+00:00",
    "season": 2024,
    "home": "Bayern München",
    "away": "Bayer Leverkusen",
    "home_id": 157,
    "away_id": 168,
    "home_score": 3,
    "away_score": 0,
    "points": 0,
    "is_home": false,
    "corners_for": 0,
    "corners_ag": 0
  },
  {
    "date": "2025-03-08T14:30:00+00:00",
    "season": 2024,
    "home": "Bayer Leverkusen",
    "away": "Werder Bremen",
    "home_id": 168,
    "away_id": 162,
    "home_score": 0,
    "away_score": 2,
    "points": 0,
    "is_home": true,
    "corners_for": 0,
    "corners_ag": 0
  },
  {
    "date": "2025-03-11T20:00:00+00:00",
    "season": 2024,
    "home": "Bayer Leverkusen",
    "away": "Bayern München",
    "home_id": 168,
    "away_id": 157,
    "home_score": 0,
    "away_score": 2,
    "points": 0,
    "is_home": true,
    "corners_for": 0,
    "corners_ag": 0
  },
  {
    "date": "2025-03-16T18:30:00+00:00",
    "season": 2024,
    "home": "VfB Stuttgart",
    "away": "Bayer Leverkusen",
    "home_id": 172,
    "away_id": 168,
    "home_score": 3,
    "away_score": 4,
    "points": 3,
    "is_home": false,
    "corners_for": 0,
    "corners_ag": 0
  },
  {
    "date": "2025-03-28T19:30:00+00:00",
    "season": 2024,
    "home": "Bayer Leverkusen",
    "away": "VfL Bochum",
    "home_id": 168,
    "away_id": 176,
    "home_score": 3,
    "away_score": 1,
    "points": 3,
    "is_home": true,
    "corners_for": 0,
    "corners_ag": 0
  },
  {
    "date": "2025-04-01T18:45:00+00:00",
    "season": 2024,
    "home": "Arminia Bielefeld",
    "away": "Bayer Leverkusen",
    "home_id": 188,
    "away_id": 168,
    "home_score": 2,
    "away_score": 1,
    "points": 0,
    "is_home": false,
    "corners_for": 0,
    "corners_ag": 0
  },
  {
    "date": "2025-04-05T13:30:00+00:00",
    "season": 2024,
    "home": "1. FC Heidenheim",
    "away": "Bayer Leverkusen",
    "home_id": 180,
    "away_id": 168,
    "home_score": 0,
    "away_score": 1,
    "points": 3,
    "is_home": false,
    "corners_for": 0,
    "corners_ag": 0
  },
  {
    "date": "2025-04-12T13:30:00+00:00",
    "season": 2024,
    "home": "Bayer Leverkusen",
    "away": "Union Berlin",
    "home_id": 168,
    "away_id": 182,
    "home_score": 0,
    "away_score": 0,
    "points": 1,
    "is_home": true,
    "corners_for": 0,
    "corners_ag": 0
  },
  {
    "date": "2025-04-20T17:30:00+00:00",
    "season": 2024,
    "home": "FC St. Pauli",
    "away": "Bayer Leverkusen",
    "home_id": 186,
    "away_id": 168,
    "home_score": 1,
    "away_score": 1,
    "points": 1,
    "is_home": false,
    "corners_for": 0,
    "corners_ag": 0
  },
  {
    "date": "2025-04-26T13:30:00+00:00",
    "season": 2024,
    "home": "Bayer Leverkusen",
    "away": "FC Augsburg",
    "home_id": 168,
    "away_id": 170,
    "home_score": 2,
    "away_score": 0,
    "points": 3,
    "is_home": true,
    "corners_for": 0,
    "corners_ag": 0
  },
  {
    "date": "2025-05-04T15:30:00+00:00",
    "season": 2024,
    "home": "SC Freiburg",
    "away": "Bayer Leverkusen",
    "home_id": 160,
    "away_id": 168,
    "home_score": 2,
    "away_score": 2,
    "points": 1,
    "is_home": false,
    "corners_for": 0,
    "corners_ag": 0
  },
  {
    "date": "2025-05-11T13:30:00+00:00",
    "season": 2024,
    "home": "Bayer Leverkusen",
    "away": "Borussia Dortmund",
    "home_id": 168,
    "away_id": 165,
    "home_score": 2,
    "away_score": 4,
    "points": 0,
    "is_home": true,
    "corners_for": 0,
    "corners_ag": 0
  },
  {
    "date": "2025-05-17T13:30:00+00:00",
    "season": 2024,
    "home": "FSV Mainz 05",
    "away": "Bayer Leverkusen",
    "home_id": 164,
    "away_id": 168,
    "home_score": 2,
    "away_score": 2,
    "points": 1,
    "is_home": false,
    "corners_for": 0,
    "corners_ag": 0
  },
  {
    "date": "2025-07-18T17:30:00+00:00",
    "season": 2025,
    "home": "Flamengo U20",
    "away": "Bayer Leverkusen",
    "home_id": 11054,
    "away_id": 168,
    "home_score": 5,
    "away_score": 1,
    "points": 0,
    "is_home": false,
    "corners_for": 0,
    "corners_ag": 0
  },
  {
    "date": "2025-07-27T16:00:00+00:00",
    "season": 2025,
    "home": "VfL Bochum",
    "away": "Bayer Leverkusen",
    "home_id": 176,
    "away_id": 168,
    "home_score": 0,
    "away_score": 2,
    "points": 3,
    "is_home": false,
    "corners_for": 0,
    "corners_ag": 0
  },
  {
    "date": "2025-08-01T17:00:00+00:00",
    "season": 2025,
    "home": "Fortuna Sittard",
    "away": "Bayer Leverkusen",
    "home_id": 205,
    "away_id": 168,
    "home_score": 1,
    "away_score": 2,
    "points": 3,
    "is_home": false,
    "corners_for": 0,
    "corners_ag": 0
  },
  {
    "date": "2025-08-05T16:00:00+00:00",
    "season": 2025,
    "home": "Bayer Leverkusen",
    "away": "Pisa",
    "home_id": 168,
    "away_id": 801,
    "home_score": 3,
    "away_score": 0,
    "points": 3,
    "is_home": true,
    "corners_for": 0,
    "corners_ag": 0
  },
  {
    "date": "2025-08-08T18:00:00+00:00",
    "season": 2025,
    "home": "Chelsea",
    "away": "Bayer Leverkusen",
    "home_id": 49,
    "away_id": 168,
    "home_score": 2,
    "away_score": 0,
    "points": 0,
    "is_home": false,
    "corners_for": 0,
    "corners_ag": 0
  },
  {
    "date": "2025-08-15T16:00:00+00:00",
    "season": 2025,
    "home": "SG Sonnenhof Grossaspach",
    "away": "Bayer Leverkusen",
    "home_id": 1317,
    "away_id": 168,
    "home_score": 0,
    "away_score": 4,
    "points": 3,
    "is_home": false,
    "corners_for": 0,
    "corners_ag": 0
  },
  {
    "date": "2025-08-23T13:30:00+00:00",
    "season": 2025,
    "home": "Bayer Leverkusen",
    "away": "1899 Hoffenheim",
    "home_id": 168,
    "away_id": 167,
    "home_score": 1,
    "away_score": 2,
    "points": 0,
    "is_home": true,
    "corners_for": 0,
    "corners_ag": 0
  },
  {
    "date": "2025-08-30T13:30:00+00:00",
    "season": 2025,
    "home": "Werder Bremen",
    "away": "Bayer Leverkusen",
    "home_id": 162,
    "away_id": 168,
    "home_score": 3,
    "away_score": 3,
    "points": 1,
    "is_home": false,
    "corners_for": 0,
    "corners_ag": 0
  },
  {
    "date": "2025-09-12T18:30:00+00:00",
    "season": 2025,
    "home": "Bayer Leverkusen",
    "away": "Eintracht Frankfurt",
    "home_id": 168,
    "away_id": 169,
    "home_score": 3,
    "away_score": 1,
    "points": 3,
    "is_home": true,
    "corners_for": 0,
    "corners_ag": 0
  },
  {
    "date": "2025-09-18T16:45:00+00:00",
    "season": 2025,
    "home": "FC Copenhagen",
    "away": "Bayer Leverkusen",
    "home_id": 400,
    "away_id": 168,
    "home_score": 2,
    "away_score": 2,
    "points": 1,
    "is_home": false,
    "corners_for": 0,
    "corners_ag": 0
  },
  {
    "date": "2025-09-21T15:30:00+00:00",
    "season": 2025,
    "home": "Bayer Leverkusen",
    "away": "Borussia Mönchengladbach",
    "home_id": 168,
    "away_id": 163,
    "home_score": 1,
    "away_score": 1,
    "points": 1,
    "is_home": true,
    "corners_for": 0,
    "corners_ag": 0
  },
  {
    "date": "2025-09-27T13:30:00+00:00",
    "season": 2025,
    "home": "FC St. Pauli",
    "away": "Bayer Leverkusen",
    "home_id": 186,
    "away_id": 168,
    "home_score": 1,
    "away_score": 2,
    "points": 3,
    "is_home": false,
    "corners_for": 0,
    "corners_ag": 0
  },
  {
    "date": "2025-10-01T19:00:00+00:00",
    "season": 2025,
    "home": "Bayer Leverkusen",
    "away": "PSV Eindhoven",
    "home_id": 168,
    "away_id": 197,
    "home_score": 1,
    "away_score": 1,
    "points": 1,
    "is_home": true,
    "corners_for": 0,
    "corners_ag": 0
  },
  {
    "date": "2025-10-04T13:30:00+00:00",
    "season": 2025,
    "home": "Bayer Leverkusen",
    "away": "Union Berlin",
    "home_id": 168,
    "away_id": 182,
    "home_score": 2,
    "away_score": 0,
    "points": 3,
    "is_home": true,
    "corners_for": 0,
    "corners_ag": 0
  },
  {
    "date": "2025-10-18T13:30:00+00:00",
    "season": 2025,
    "home": "FSV Mainz 05",
    "away": "Bayer Leverkusen",
    "home_id": 164,
    "away_id": 168,
    "home_score": 3,
    "away_score": 4,
    "points": 3,
    "is_home": false,
    "corners_for": 0,
    "corners_ag": 0
  },
  {
    "date": "2025-10-21T19:00:00+00:00",
    "season": 2025,
    "home": "Bayer Leverkusen",
    "away": "Paris Saint Germain",
    "home_id": 168,
    "away_id": 85,
    "home_score": 2,
    "away_score": 7,
    "points": 0,
    "is_home": true,
    "corners_for": 0,
    "corners_ag": 0
  },
  {
    "date": "2025-10-26T14:30:00+00:00",
    "season": 2025,
    "home": "Bayer Leverkusen",
    "away": "SC Freiburg",
    "home_id": 168,
    "away_id": 160,
    "home_score": 2,
    "away_score": 0,
    "points": 3,
    "is_home": true,
    "corners_for": 0,
    "corners_ag": 0
  },
  {
    "date": "2025-11-01T17:30:00+00:00",
    "season": 2025,
    "home": "Bayern München",
    "away": "Bayer Leverkusen",
    "home_id": 157,
    "away_id": 168,
    "home_score": 3,
    "away_score": 0,
    "points": 0,
    "is_home": false,
    "corners_for": 0,
    "corners_ag": 0
  },
  {
    "date": "2025-11-05T20:00:00+00:00",
    "season": 2025,
    "home": "Benfica",
    "away": "Bayer Leverkusen",
    "home_id": 211,
    "away_id": 168,
    "home_score": 0,
    "away_score": 1,
    "points": 3,
    "is_home": false,
    "corners_for": 0,
    "corners_ag": 0
  },
  {
    "date": "2025-11-08T14:30:00+00:00",
    "season": 2025,
    "home": "Bayer Leverkusen",
    "away": "1. FC Heidenheim",
    "home_id": 168,
    "away_id": 180,
    "home_score": 6,
    "away_score": 0,
    "points": 3,
    "is_home": true,
    "corners_for": 0,
    "corners_ag": 0
  },
  {
    "date": "2025-11-22T14:30:00+00:00",
    "season": 2025,
    "home": "VfL Wolfsburg",
    "away": "Bayer Leverkusen",
    "home_id": 161,
    "away_id": 168,
    "home_score": 1,
    "away_score": 3,
    "points": 3,
    "is_home": false,
    "corners_for": 0,
    "corners_ag": 0
  },
  {
    "date": "2025-11-25T20:00:00+00:00",
    "season": 2025,
    "home": "Manchester City",
    "away": "Bayer Leverkusen",
    "home_id": 50,
    "away_id": 168,
    "home_score": 0,
    "away_score": 2,
    "points": 3,
    "is_home": false,
    "corners_for": 0,
    "corners_ag": 0
  },
  {
    "date": "2025-11-29T17:30:00+00:00",
    "season": 2025,
    "home": "Bayer Leverkusen",
    "away": "Borussia Dortmund",
    "home_id": 168,
    "away_id": 165,
    "home_score": 1,
    "away_score": 2,
    "points": 0,
    "is_home": true,
    "corners_for": 0,
    "corners_ag": 0
  },
  {
    "date": "2025-12-02T20:00:00+00:00",
    "season": 2025,
    "home": "Borussia Dortmund",
    "away": "Bayer Leverkusen",
    "home_id": 165,
    "away_id": 168,
    "home_score": 0,
    "away_score": 1,
    "points": 3,
    "is_home": false,
    "corners_for": 0,
    "corners_ag": 0
  },
  {
    "date": "2025-12-06T14:30:00+00:00",
    "season": 2025,
    "home": "FC Augsburg",
    "away": "Bayer Leverkusen",
    "home_id": 170,
    "away_id": 168,
    "home_score": 2,
    "away_score": 0,
    "points": 0,
    "is_home": false,
    "corners_for": 0,
    "corners_ag": 0
  },
  {
    "date": "2025-12-10T20:00:00+00:00",
    "season": 2025,
    "home": "Bayer Leverkusen",
    "away": "Newcastle",
    "home_id": 168,
    "away_id": 34,
    "home_score": 2,
    "away_score": 2,
    "points": 1,
    "is_home": true,
    "corners_for": 0,
    "corners_ag": 0
  },
  {
    "date": "2025-12-13T17:30:00+00:00",
    "season": 2025,
    "home": "Bayer Leverkusen",
    "away": "1. FC Köln",
    "home_id": 168,
    "away_id": 192,
    "home_score": 2,
    "away_score": 0,
    "points": 3,
    "is_home": true,
    "corners_for": 0,
    "corners_ag": 0
  },
  {
    "date": "2025-12-20T17:30:00+00:00",
    "season": 2025,
    "home": "RB Leipzig",
    "away": "Bayer Leverkusen",
    "home_id": 173,
    "away_id": 168,
    "home_score": 1,
    "away_score": 3,
    "points": 3,
    "is_home": false,
    "corners_for": 0,
    "corners_ag": 0
  },
  {
    "date": "2026-01-10T17:30:00+00:00",
    "season": 2025,
    "home": "Bayer Leverkusen",
    "away": "VfB Stuttgart",
    "home_id": 168,
    "away_id": 172,
    "home_score": 1,
    "away_score": 4,
    "points": 0,
    "is_home": true,
    "corners_for": 0,
    "corners_ag": 0
  },
  {
    "date": "2026-01-17T14:30:00+00:00",
    "season": 2025,
    "home": "1899 Hoffenheim",
    "away": "Bayer Leverkusen",
    "home_id": 167,
    "away_id": 168,
    "home_score": 1,
    "away_score": 0,
    "points": 0,
    "is_home": false,
    "corners_for": 0,
    "corners_ag": 0
  },
  {
    "date": "2026-01-20T20:00:00+00:00",
    "season": 2025,
    "home": "Olympiakos Piraeus",
    "away": "Bayer Leverkusen",
    "home_id": 553,
    "away_id": 168,
    "home_score": 2,
    "away_score": 0,
    "points": 0,
    "is_home": false,
    "corners_for": 0,
    "corners_ag": 0
  },
  {
    "date": "2026-01-24T14:30:00+00:00",
    "season": 2025,
    "home": "Bayer Leverkusen",
    "away": "Werder Bremen",
    "home_id": 168,
    "away_id": 162,
    "home_score": 1,
    "away_score": 0,
    "points": 3,
    "is_home": true,
    "corners_for": 0,
    "corners_ag": 0
  },
  {
    "date": "2026-01-28T20:00:00+00:00",
    "season": 2025,
    "home": "Bayer Leverkusen",
    "away": "Villarreal",
    "home_id": 168,
    "away_id": 533,
    "home_score": 3,
    "away_score": 0,
    "points": 3,
    "is_home": true,
    "corners_for": 0,
    "corners_ag": 0
  },
  {
    "date": "2026-01-31T14:30:00+00:00",
    "season": 2025,
    "home": "Eintracht Frankfurt",
    "away": "Bayer Leverkusen",
    "home_id": 169,
    "away_id": 168,
    "home_score": 1,
    "away_score": 3,
    "points": 3,
    "is_home": false,
    "corners_for": 0,
    "corners_ag": 0
  },
  {
    "date": "2026-02-03T19:45:00+00:00",
    "season": 2025,
    "home": "Bayer Leverkusen",
    "away": "FC St. Pauli",
    "home_id": 168,
    "away_id": 186,
    "home_score": 3,
    "away_score": 0,
    "points": 3,
    "is_home": true,
    "corners_for": 0,
    "corners_ag": 0
  },
  {
    "date": "2026-02-07T17:30:00+00:00",
    "season": 2025,
    "home": "Borussia Mönchengladbach",
    "away": "Bayer Leverkusen",
    "home_id": 163,
    "away_id": 168,
    "home_score": 1,
    "away_score": 1,
    "points": 1,
    "is_home": false,
    "corners_for": 0,
    "corners_ag": 0
  },
  {
    "date": "2026-02-14T14:30:00+00:00",
    "season": 2025,
    "home": "Bayer Leverkusen",
    "away": "FC St. Pauli",
    "home_id": 168,
    "away_id": 186,
    "home_score": 4,
    "away_score": 0,
    "points": 3,
    "is_home": true,
    "corners_for": 0,
    "corners_ag": 0
  },
  {
    "date": "2026-02-18T20:00:00+00:00",
    "season": 2025,
    "home": "Olympiakos Piraeus",
    "away": "Bayer Leverkusen",
    "home_id": 553,
    "away_id": 168,
    "home_score": 0,
    "away_score": 2,
    "points": 3,
    "is_home": false,
    "corners_for": 0,
    "corners_ag": 0
  },
  {
    "date": "2026-02-21T14:30:00+00:00",
    "season": 2025,
    "home": "Union Berlin",
    "away": "Bayer Leverkusen",
    "home_id": 182,
    "away_id": 168,
    "home_score": 1,
    "away_score": 0,
    "points": 0,
    "is_home": false,
    "corners_for": 0,
    "corners_ag": 0
  },
  {
    "date": "2026-02-24T20:00:00+00:00",
    "season": 2025,
    "home": "Bayer Leverkusen",
    "away": "Olympiakos Piraeus",
    "home_id": 168,
    "away_id": 553,
    "home_score": 0,
    "away_score": 0,
    "points": 1,
    "is_home": true,
    "corners_for": 0,
    "corners_ag": 0
  },
  {
    "date": "2026-02-28T14:30:00+00:00",
    "season": 2025,
    "home": "Bayer Leverkusen",
    "away": "FSV Mainz 05",
    "home_id": 168,
    "away_id": 164,
    "home_score": 1,
    "away_score": 1,
    "points": 1,
    "is_home": true,
    "corners_for": 0,
    "corners_ag": 0
  },
  {
    "date": "2026-03-04T19:30:00+00:00",
    "season": 2025,
    "home": "Hamburger SV",
    "away": "Bayer Leverkusen",
    "home_id": 175,
    "away_id": 168,
    "home_score": 0,
    "away_score": 1,
    "points": 3,
    "is_home": false,
    "corners_for": 0,
    "corners_ag": 0
  },
  {
    "date": "2026-03-07T14:30:00+00:00",
    "season": 2025,
    "home": "SC Freiburg",
    "away": "Bayer Leverkusen",
    "home_id": 160,
    "away_id": 168,
    "home_score": 3,
    "away_score": 3,
    "points": 1,
    "is_home": false,
    "corners_for": 0,
    "corners_ag": 0
  },
  {
    "date": "2026-03-11T17:45:00+00:00",
    "season": 2025,
    "home": "Bayer Leverkusen",
    "away": "Arsenal",
    "home_id": 168,
    "away_id": 42,
    "home_score": 1,
    "away_score": 1,
    "points": 1,
    "is_home": true,
    "corners_for": 0,
    "corners_ag": 0
  },
  {
    "date": "2026-03-14T14:30:00+00:00",
    "season": 2025,
    "home": "Bayer Leverkusen",
    "away": "Bayern München",
    "home_id": 168,
    "away_id": 157,
    "home_score": 1,
    "away_score": 1,
    "points": 1,
    "is_home": true,
    "corners_for": 0,
    "corners_ag": 0
  },
  {
    "date": "2026-03-17T20:00:00+00:00",
    "season": 2025,
    "home": "Arsenal",
    "away": "Bayer Leverkusen",
    "home_id": 42,
    "away_id": 168,
    "home_score": 2,
    "away_score": 0,
    "points": 0,
    "is_home": false,
    "corners_for": 0,
    "corners_ag": 0
  },
  {
    "date": "2026-03-21T14:30:00+00:00",
    "season": 2025,
    "home": "1. FC Heidenheim",
    "away": "Bayer Leverkusen",
    "home_id": 180,
    "away_id": 168,
    "home_score": 3,
    "away_score": 3,
    "points": 1,
    "is_home": false,
    "corners_for": 0,
    "corners_ag": 0
  },
  {
    "date": "2026-04-04T13:30:00+00:00",
    "season": 2025,
    "home": "Bayer Leverkusen",
    "away": "VfL Wolfsburg",
    "home_id": 168,
    "away_id": 161,
    "home_score": 6,
    "away_score": 3,
    "points": 3,
    "is_home": true,
    "corners_for": 0,
    "corners_ag": 0
  },
  {
    "date": "2026-04-11T13:30:00+00:00",
    "season": 2025,
    "home": "Borussia Dortmund",
    "away": "Bayer Leverkusen",
    "home_id": 165,
    "away_id": 168,
    "home_score": 0,
    "away_score": 1,
    "points": 3,
    "is_home": false,
    "corners_for": 0,
    "corners_ag": 0
  }
]