[
  {
    "date": "2022-07-16T17:00:00+00:00",
    "season": 2022,
    "home": "1. FC Köln",
    "away": "AC Milan",
    "home_id": 192,
    "away_id": 489,
    "home_score": 1,
    "away_score": 2,
    "points": 0,
    "is_home": true,
    "corners_for": 0,
    "corners_ag": 0
  },
  {
    "date": "2022-03-23T00:00:00+00:00",
    "season": 2022,
    "home": "Siegburger SV",
    "away": "1. FC Köln",
    "home_id": 12853,
    "away_id": 192,
    "home_score": 1,
    "away_score": 8,
    "points": 3,
    "is_home": false,
    "corners_for": 0,
    "corners_ag": 0
  },
  {
    "date": "2022-07-08T16:00:00+00:00",
    "season": 2022,
    "home": "1. FC Köln",
    "away": "Austria Lustenau",
    "home_id": 192,
    "away_id": 1399,
    "home_score": 4,
    "away_score": 0,
    "points": 3,
    "is_home": true,
    "corners_for": 0,
    "corners_ag": 0
  },
  {
    "date": "2022-07-09T13:00:00+00:00",
    "season": 2022,
    "home": "1. FC Köln",
    "away": "Grasshoppers",
    "home_id": 192,
    "away_id": 1013,
    "home_score": 1,
    "away_score": 1,
    "points": 1,
    "is_home": true,
    "corners_for": 0,
    "corners_ag": 0
  },
  {
    "date": "2022-07-22T16:00:00+00:00",
    "season": 2022,
    "home": "1. FC Köln",
    "away": "NEC Nijmegen",
    "home_id": 192,
    "away_id": 413,
    "home_score": 5,
    "away_score": 0,
    "points": 3,
    "is_home": true,
    "corners_for": 0,
    "corners_ag": 0
  },
  {
    "date": "2022-08-07T15:30:00+00:00",
    "season": 2022,
    "home": "1. FC Köln",
    "away": "FC Schalke 04",
    "home_id": 192,
    "away_id": 174,
    "home_score": 3,
    "away_score": 1,
    "points": 3,
    "is_home": true,
    "corners_for": 0,
    "corners_ag": 0
  },
  {
    "date": "2022-08-13T13:30:00+00:00",
    "season": 2022,
    "home": "RB Leipzig",
    "away": "1. FC Köln",
    "home_id": 173,
    "away_id": 192,
    "home_score": 2,
    "away_score": 2,
    "points": 1,
    "is_home": false,
    "corners_for": 0,
    "corners_ag": 0
  },
  {
    "date": "2022-08-21T13:30:00+00:00",
    "season": 2022,
    "home": "Eintracht Frankfurt",
    "away": "1. FC Köln",
    "home_id": 169,
    "away_id": 192,
    "home_score": 1,
    "away_score": 1,
    "points": 1,
    "is_home": false,
    "corners_for": 0,
    "corners_ag": 0
  },
  {
    "date": "2022-08-28T13:30:00+00:00",
    "season": 2022,
    "home": "1. FC Köln",
    "away": "VfB Stuttgart",
    "home_id": 192,
    "away_id": 172,
    "home_score": 0,
    "away_score": 0,
    "points": 1,
    "is_home": true,
    "corners_for": 0,
    "corners_ag": 0
  },
  {
    "date": "2022-09-03T13:30:00+00:00",
    "season": 2022,
    "home": "VfL Wolfsburg",
    "away": "1. FC Köln",
    "home_id": 161,
    "away_id": 192,
    "home_score": 2,
    "away_score": 4,
    "points": 3,
    "is_home": false,
    "corners_for": 0,
    "corners_ag": 0
  },
  {
    "date": "2022-09-11T13:30:00+00:00",
    "season": 2022,
    "home": "1. FC Köln",
    "away": "Union Berlin",
    "home_id": 192,
    "away_id": 182,
    "home_score": 0,
    "away_score": 1,
    "points": 0,
    "is_home": true,
    "corners_for": 0,
    "corners_ag": 0
  },
  {
    "date": "2022-09-18T15:30:00+00:00",
    "season": 2022,
    "home": "Vfl Bochum",
    "away": "1. FC Köln",
    "home_id": 176,
    "away_id": 192,
    "home_score": 1,
    "away_score": 1,
    "points": 1,
    "is_home": false,
    "corners_for": 0,
    "corners_ag": 0
  },
  {
    "date": "2022-10-01T13:30:00+00:00",
    "season": 2022,
    "home": "1. FC Köln",
    "away": "Borussia Dortmund",
    "home_id": 192,
    "away_id": 165,
    "home_score": 3,
    "away_score": 2,
    "points": 3,
    "is_home": true,
    "corners_for": 0,
    "corners_ag": 0
  },
  {
    "date": "2022-10-09T13:30:00+00:00",
    "season": 2022,
    "home": "Borussia Monchengladbach",
    "away": "1. FC Köln",
    "home_id": 163,
    "away_id": 192,
    "home_score": 5,
    "away_score": 2,
    "points": 0,
    "is_home": false,
    "corners_for": 0,
    "corners_ag": 0
  },
  {
    "date": "2022-10-16T13:30:00+00:00",
    "season": 2022,
    "home": "1. FC Köln",
    "away": "FC Augsburg",
    "home_id": 192,
    "away_id": 170,
    "home_score": 3,
    "away_score": 2,
    "points": 3,
    "is_home": true,
    "corners_for": 0,
    "corners_ag": 0
  },
  {
    "date": "2022-10-21T18:30:00+00:00",
    "season": 2022,
    "home": "FSV Mainz 05",
    "away": "1. FC Köln",
    "home_id": 164,
    "away_id": 192,
    "home_score": 5,
    "away_score": 0,
    "points": 0,
    "is_home": false,
    "corners_for": 0,
    "corners_ag": 0
  },
  {
    "date": "2022-10-30T18:30:00+00:00",
    "season": 2022,
    "home": "1. FC Köln",
    "away": "1899 Hoffenheim",
    "home_id": 192,
    "away_id": 167,
    "home_score": 1,
    "away_score": 1,
    "points": 1,
    "is_home": true,
    "corners_for": 0,
    "corners_ag": 0
  },
  {
    "date": "2022-11-06T16:30:00+00:00",
    "season": 2022,
    "home": "SC Freiburg",
    "away": "1. FC Köln",
    "home_id": 160,
    "away_id": 192,
    "home_score": 2,
    "away_score": 0,
    "points": 0,
    "is_home": false,
    "corners_for": 0,
    "corners_ag": 0
  },
  {
    "date": "2022-11-09T17:30:00+00:00",
    "season": 2022,
    "home": "1. FC Köln",
    "away": "Bayer Leverkusen",
    "home_id": 192,
    "away_id": 168,
    "home_score": 1,
    "away_score": 2,
    "points": 0,
    "is_home": true,
    "corners_for": 0,
    "corners_ag": 0
  },
  {
    "date": "2022-11-12T14:30:00+00:00",
    "season": 2022,
    "home": "Hertha Berlin",
    "away": "1. FC Köln",
    "home_id": 159,
    "away_id": 192,
    "home_score": 2,
    "away_score": 0,
    "points": 0,
    "is_home": false,
    "corners_for": 0,
    "corners_ag": 0
  },
  {
    "date": "2023-01-21T17:30:00+00:00",
    "season": 2022,
    "home": "1. FC Köln",
    "away": "Werder Bremen",
    "home_id": 192,
    "away_id": 162,
    "home_score": 7,
    "away_score": 1,
    "points": 3,
    "is_home": true,
    "corners_for": 0,
    "corners_ag": 0
  },
  {
    "date": "2023-01-24T19:30:00+00:00",
    "season": 2022,
    "home": "Bayern Munich",
    "away": "1. FC Köln",
    "home_id": 157,
    "away_id": 192,
    "home_score": 1,
    "away_score": 1,
    "points": 1,
    "is_home": false,
    "corners_for": 0,
    "corners_ag": 0
  },
  {
    "date": "2023-01-29T14:30:00+00:00",
    "season": 2022,
    "home": "FC Schalke 04",
    "away": "1. FC Köln",
    "home_id": 174,
    "away_id": 192,
    "home_score": 0,
    "away_score": 0,
    "points": 1,
    "is_home": false,
    "corners_for": 0,
    "corners_ag": 0
  },
  {
    "date": "2023-02-04T14:30:00+00:00",
    "season": 2022,
    "home": "1. FC Köln",
    "away": "RB Leipzig",
    "home_id": 192,
    "away_id": 173,
    "home_score": 0,
    "away_score": 0,
    "points": 1,
    "is_home": true,
    "corners_for": 0,
    "corners_ag": 0
  },
  {
    "date": "2023-02-12T16:30:00+00:00",
    "season": 2022,
    "home": "1. FC Köln",
    "away": "Eintracht Frankfurt",
    "home_id": 192,
    "away_id": 169,
    "home_score": 3,
    "away_score": 0,
    "points": 3,
    "is_home": true,
    "corners_for": 0,
    "corners_ag": 0
  },
  {
    "date": "2023-02-18T14:30:00+00:00",
    "season": 2022,
    "home": "VfB Stuttgart",
    "away": "1. FC Köln",
    "home_id": 172,
    "away_id": 192,
    "home_score": 3,
    "away_score": 0,
    "points": 0,
    "is_home": false,
    "corners_for": 0,
    "corners_ag": 0
  },
  {
    "date": "2023-02-25T14:30:00+00:00",
    "season": 2022,
    "home": "1. FC Köln",
    "away": "VfL Wolfsburg",
    "home_id": 192,
    "away_id": 161,
    "home_score": 0,
    "away_score": 2,
    "points": 0,
    "is_home": true,
    "corners_for": 0,
    "corners_ag": 0
  },
  {
    "date": "2023-03-04T14:30:00+00:00",
    "season": 2022,
    "home": "Union Berlin",
    "away": "1. FC Köln",
    "home_id": 182,
    "away_id": 192,
    "home_score": 0,
    "away_score": 0,
    "points": 1,
    "is_home": false,
    "corners_for": 0,
    "corners_ag": 0
  },
  {
    "date": "2023-03-10T19:30:00+00:00",
    "season": 2022,
    "home": "1. FC Köln",
    "away": "Vfl Bochum",
    "home_id": 192,
    "away_id": 176,
    "home_score": 0,
    "away_score": 2,
    "points": 0,
    "is_home": true,
    "corners_for": 0,
    "corners_ag": 0
  },
  {
    "date": "2023-03-18T17:30:00+00:00",
    "season": 2022,
    "home": "Borussia Dortmund",
    "away": "1. FC Köln",
    "home_id": 165,
    "away_id": 192,
    "home_score": 6,
    "away_score": 1,
    "points": 0,
    "is_home": false,
    "corners_for": 0,
    "corners_ag": 0
  },
  {
    "date": "2023-04-02T13:30:00+00:00",
    "season": 2022,
    "home": "1. FC Köln",
    "away": "Borussia Monchengladbach",
    "home_id": 192,
    "away_id": 163,
    "home_score": 0,
    "away_score": 0,
    "points": 1,
    "is_home": true,
    "corners_for": 0,
    "corners_ag": 0
  },
  {
    "date": "2023-04-08T13:30:00+00:00",
    "season": 2022,
    "home": "FC Augsburg",
    "away": "1. FC Köln",
    "home_id": 170,
    "away_id": 192,
    "home_score": 1,
    "away_score": 3,
    "points": 3,
    "is_home": false,
    "corners_for": 0,
    "corners_ag": 0
  },
  {
    "date": "2023-04-15T13:30:00+00:00",
    "season": 2022,
    "home": "1. FC Köln",
    "away": "FSV Mainz 05",
    "home_id": 192,
    "away_id": 164,
    "home_score": 1,
    "away_score": 1,
    "points": 1,
    "is_home": true,
    "corners_for": 0,
    "corners_ag": 0
  },
  {
    "date": "2023-04-22T13:30:00+00:00",
    "season": 2022,
    "home": "1899 Hoffenheim",
    "away": "1. FC Köln",
    "home_id": 167,
    "away_id": 192,
    "home_score": 1,
    "away_score": 3,
    "points": 3,
    "is_home": false,
    "corners_for": 0,
    "corners_ag": 0
  },
  {
    "date": "2023-04-29T13:30:00+00:00",
    "season": 2022,
    "home": "1. FC Köln",
    "away": "SC Freiburg",
    "home_id": 192,
    "away_id": 160,
    "home_score": 0,
    "away_score": 1,
    "points": 0,
    "is_home": true,
    "corners_for": 0,
    "corners_ag": 0
  },
  {
    "date": "2023-05-05T18:30:00+00:00",
    "season": 2022,
    "home": "Bayer Leverkusen",
    "away": "1. FC Köln",
    "home_id": 168,
    "away_id": 192,
    "home_score": 1,
    "away_score": 2,
    "points": 3,
    "is_home": false,
    "corners_for": 0,
    "corners_ag": 0
  },
  {
    "date": "2023-05-12T18:30:00+00:00",
    "season": 2022,
    "home": "1. FC Köln",
    "away": "Hertha Berlin",
    "home_id": 192,
    "away_id": 159,
    "home_score": 5,
    "away_score": 2,
    "points": 3,
    "is_home": true,
    "corners_for": 0,
    "corners_ag": 0
  },
  {
    "date": "2023-05-20T13:30:00+00:00",
    "season": 2022,
    "home": "Werder Bremen",
    "away": "1. FC Köln",
    "home_id": 162,
    "away_id": 192,
    "home_score": 1,
    "away_score": 1,
    "points": 1,
    "is_home": false,
    "corners_for": 0,
    "corners_ag": 0
  },
  {
    "date": "2023-05-27T13:30:00+00:00",
    "season": 2022,
    "home": "1. FC Köln",
    "away": "Bayern Munich",
    "home_id": 192,
    "away_id": 157,
    "home_score": 1,
    "away_score": 2,
    "points": 0,
    "is_home": true,
    "corners_for": 0,
    "corners_ag": 0
  },
  {
    "date": "2022-07-01T16:00:00+00:00",
    "season": 2022,
    "home": "Mondorf",
    "away": "1. FC Köln",
    "home_id": 19253,
    "away_id": 192,
    "home_score": 1,
    "away_score": 12,
    "points": 3,
    "is_home": false,
    "corners_for": 0,
    "corners_ag": 0
  },
  {
    "date": "2022-07-17T13:30:00+00:00",
    "season": 2022,
    "home": "Kickers Offenbach",
    "away": "1. FC Köln",
    "home_id": 1628,
    "away_id": 192,
    "home_score": 0,
    "away_score": 2,
    "points": 3,
    "is_home": false,
    "corners_for": 0,
    "corners_ag": 0
  },
  {
    "date": "2022-07-08T16:00:00+00:00",
    "season": 2022,
    "home": "Austria Lustenau",
    "away": "1. FC Köln",
    "home_id": 1399,
    "away_id": 192,
    "home_score": 0,
    "away_score": 4,
    "points": 3,
    "is_home": false,
    "corners_for": 0,
    "corners_ag": 0
  },
  {
    "date": "2022-08-18T18:30:00+00:00",
    "season": 2022,
    "home": "1. FC Köln",
    "away": "Fehérvár FC",
    "home_id": 192,
    "away_id": 610,
    "home_score": 1,
    "away_score": 2,
    "points": 0,
    "is_home": true,
    "corners_for": 0,
    "corners_ag": 0
  },
  {
    "date": "2022-08-25T17:00:00+00:00",
    "season": 2022,
    "home": "Fehérvár FC",
    "away": "1. FC Köln",
    "home_id": 610,
    "away_id": 192,
    "home_score": 0,
    "away_score": 3,
    "points": 3,
    "is_home": false,
    "corners_for": 0,
    "corners_ag": 0
  },
  {
    "date": "2022-09-08T16:45:00+00:00",
    "season": 2022,
    "home": "Nice",
    "away": "1. FC Köln",
    "home_id": 84,
    "away_id": 192,
    "home_score": 1,
    "away_score": 1,
    "points": 1,
    "is_home": false,
    "corners_for": 0,
    "corners_ag": 0
  },
  {
    "date": "2022-09-15T19:00:00+00:00",
    "season": 2022,
    "home": "1. FC Köln",
    "away": "Slovácko",
    "home_id": 192,
    "away_id": 3719,
    "home_score": 4,
    "away_score": 2,
    "points": 3,
    "is_home": true,
    "corners_for": 0,
    "corners_ag": 0
  },
  {
    "date": "2022-10-06T19:00:00+00:00",
    "season": 2022,
    "home": "1. FC Köln",
    "away": "FK Partizan",
    "home_id": 192,
    "away_id": 573,
    "home_score": 0,
    "away_score": 1,
    "points": 0,
    "is_home": true,
    "corners_for": 0,
    "corners_ag": 0
  },
  {
    "date": "2022-10-13T16:45:00+00:00",
    "season": 2022,
    "home": "FK Partizan",
    "away": "1. FC Köln",
    "home_id": 573,
    "away_id": 192,
    "home_score": 2,
    "away_score": 0,
    "points": 0,
    "is_home": false,
    "corners_for": 0,
    "corners_ag": 0
  },
  {
    "date": "2022-10-28T16:45:00+00:00",
    "season": 2022,
    "home": "Slovácko",
    "away": "1. FC Köln",
    "home_id": 3719,
    "away_id": 192,
    "home_score": 0,
    "away_score": 1,
    "points": 3,
    "is_home": false,
    "corners_for": 0,
    "corners_ag": 0
  },
  {
    "date": "2022-11-03T20:00:00+00:00",
    "season": 2022,
    "home": "1. FC Köln",
    "away": "Nice",
    "home_id": 192,
    "away_id": 84,
    "home_score": 2,
    "away_score": 2,
    "points": 1,
    "is_home": true,
    "corners_for": 0,
    "corners_ag": 0
  },
  {
    "date": "2022-11-19T21:00:00+00:00",
    "season": 2022,
    "home": "1. FC Köln",
    "away": "VfB Stuttgart",
    "home_id": 192,
    "away_id": 172,
    "home_score": 2,
    "away_score": 4,
    "points": 0,
    "is_home": true,
    "corners_for": 0,
    "corners_ag": 0
  },
  {
    "date": "2022-12-21T12:00:00+00:00",
    "season": 2022,
    "home": "1. FC Köln",
    "away": "SV Meppen",
    "home_id": 192,
    "away_id": 1318,
    "home_score": 1,
    "away_score": 0,
    "points": 3,
    "is_home": true,
    "corners_for": 0,
    "corners_ag": 0
  }
]