[
  {
    "date": "2024-08-18T18:45:00+00:00",
    "season": 2024,
    "home": "Cagliari",
    "away": "AS Roma",
    "home_id": 490,
    "away_id": 497,
    "home_score": 0,
    "away_score": 0,
    "points": 1,
    "is_home": true,
    "corners_for": 0,
    "corners_ag": 0
  },
  {
    "date": "2024-08-26T16:30:00+00:00",
    "season": 2024,
    "home": "Cagliari",
    "away": "Como",
    "home_id": 490,
    "away_id": 895,
    "home_score": 1,
    "away_score": 1,
    "points": 1,
    "is_home": true,
    "corners_for": 0,
    "corners_ag": 0
  },
  {
    "date": "2024-08-31T16:30:00+00:00",
    "season": 2024,
    "home": "Lecce",
    "away": "Cagliari",
    "home_id": 867,
    "away_id": 490,
    "home_score": 1,
    "away_score": 0,
    "points": 0,
    "is_home": false,
    "corners_for": 0,
    "corners_ag": 0
  },
  {
    "date": "2024-09-15T16:00:00+00:00",
    "season": 2024,
    "home": "Cagliari",
    "away": "Napoli",
    "home_id": 490,
    "away_id": 492,
    "home_score": 0,
    "away_score": 4,
    "points": 0,
    "is_home": true,
    "corners_for": 0,
    "corners_ag": 0
  },
  {
    "date": "2024-09-20T16:30:00+00:00",
    "season": 2024,
    "home": "Cagliari",
    "away": "Empoli",
    "home_id": 490,
    "away_id": 511,
    "home_score": 0,
    "away_score": 2,
    "points": 0,
    "is_home": true,
    "corners_for": 0,
    "corners_ag": 0
  },
  {
    "date": "2024-09-30T18:45:00+00:00",
    "season": 2024,
    "home": "Parma",
    "away": "Cagliari",
    "home_id": 523,
    "away_id": 490,
    "home_score": 2,
    "away_score": 3,
    "points": 3,
    "is_home": false,
    "corners_for": 0,
    "corners_ag": 0
  },
  {
    "date": "2024-10-06T10:30:00+00:00",
    "season": 2024,
    "home": "Juventus",
    "away": "Cagliari",
    "home_id": 496,
    "away_id": 490,
    "home_score": 1,
    "away_score": 1,
    "points": 1,
    "is_home": false,
    "corners_for": 0,
    "corners_ag": 0
  },
  {
    "date": "2024-10-20T16:00:00+00:00",
    "season": 2024,
    "home": "Cagliari",
    "away": "Torino",
    "home_id": 490,
    "away_id": 503,
    "home_score": 3,
    "away_score": 2,
    "points": 3,
    "is_home": true,
    "corners_for": 0,
    "corners_ag": 0
  },
  {
    "date": "2024-10-25T16:30:00+00:00",
    "season": 2024,
    "home": "Udinese",
    "away": "Cagliari",
    "home_id": 494,
    "away_id": 490,
    "home_score": 2,
    "away_score": 0,
    "points": 0,
    "is_home": false,
    "corners_for": 0,
    "corners_ag": 0
  },
  {
    "date": "2024-10-29T17:30:00+00:00",
    "season": 2024,
    "home": "Cagliari",
    "away": "Bologna",
    "home_id": 490,
    "away_id": 500,
    "home_score": 0,
    "away_score": 2,
    "points": 0,
    "is_home": true,
    "corners_for": 0,
    "corners_ag": 0
  },
  {
    "date": "2024-11-04T19:45:00+00:00",
    "season": 2024,
    "home": "Lazio",
    "away": "Cagliari",
    "home_id": 487,
    "away_id": 490,
    "home_score": 2,
    "away_score": 1,
    "points": 0,
    "is_home": false,
    "corners_for": 0,
    "corners_ag": 0
  },
  {
    "date": "2024-11-09T17:00:00+00:00",
    "season": 2024,
    "home": "Cagliari",
    "away": "AC Milan",
    "home_id": 490,
    "away_id": 489,
    "home_score": 3,
    "away_score": 3,
    "points": 1,
    "is_home": true,
    "corners_for": 0,
    "corners_ag": 0
  },
  {
    "date": "2024-11-24T11:30:00+00:00",
    "season": 2024,
    "home": "Genoa",
    "away": "Cagliari",
    "home_id": 495,
    "away_id": 490,
    "home_score": 2,
    "away_score": 2,
    "points": 1,
    "is_home": false,
    "corners_for": 0,
    "corners_ag": 0
  },
  {
    "date": "2024-11-29T19:45:00+00:00",
    "season": 2024,
    "home": "Cagliari",
    "away": "Hellas Verona",
    "home_id": 490,
    "away_id": 504,
    "home_score": 1,
    "away_score": 0,
    "points": 3,
    "is_home": true,
    "corners_for": 0,
    "corners_ag": 0
  },
  {
    "date": "2024-12-08T11:30:00+00:00",
    "season": 2024,
    "home": "Fiorentina",
    "away": "Cagliari",
    "home_id": 502,
    "away_id": 490,
    "home_score": 1,
    "away_score": 0,
    "points": 0,
    "is_home": false,
    "corners_for": 0,
    "corners_ag": 0
  },
  {
    "date": "2024-12-14T14:00:00+00:00",
    "season": 2024,
    "home": "Cagliari",
    "away": "Atalanta",
    "home_id": 490,
    "away_id": 499,
    "home_score": 0,
    "away_score": 1,
    "points": 0,
    "is_home": true,
    "corners_for": 0,
    "corners_ag": 0
  },
  {
    "date": "2024-12-22T14:00:00+00:00",
    "season": 2024,
    "home": "Venezia",
    "away": "Cagliari",
    "home_id": 517,
    "away_id": 490,
    "home_score": 2,
    "away_score": 1,
    "points": 0,
    "is_home": false,
    "corners_for": 0,
    "corners_ag": 0
  },
  {
    "date": "2024-12-28T17:00:00+00:00",
    "season": 2024,
    "home": "Cagliari",
    "away": "Inter",
    "home_id": 490,
    "away_id": 505,
    "home_score": 0,
    "away_score": 3,
    "points": 0,
    "is_home": true,
    "corners_for": 0,
    "corners_ag": 0
  },
  {
    "date": "2025-01-05T11:30:00+00:00",
    "season": 2024,
    "home": "Monza",
    "away": "Cagliari",
    "home_id": 1579,
    "away_id": 490,
    "home_score": 1,
    "away_score": 2,
    "points": 3,
    "is_home": false,
    "corners_for": 0,
    "corners_ag": 0
  },
  {
    "date": "2025-01-11T19:45:00+00:00",
    "season": 2024,
    "home": "AC Milan",
    "away": "Cagliari",
    "home_id": 489,
    "away_id": 490,
    "home_score": 1,
    "away_score": 1,
    "points": 1,
    "is_home": false,
    "corners_for": 0,
    "corners_ag": 0
  },
  {
    "date": "2025-01-19T14:00:00+00:00",
    "season": 2024,
    "home": "Cagliari",
    "away": "Lecce",
    "home_id": 490,
    "away_id": 867,
    "home_score": 4,
    "away_score": 1,
    "points": 3,
    "is_home": true,
    "corners_for": 0,
    "corners_ag": 0
  },
  {
    "date": "2025-01-24T19:45:00+00:00",
    "season": 2024,
    "home": "Torino",
    "away": "Cagliari",
    "home_id": 503,
    "away_id": 490,
    "home_score": 2,
    "away_score": 0,
    "points": 0,
    "is_home": false,
    "corners_for": 0,
    "corners_ag": 0
  },
  {
    "date": "2025-02-03T19:45:00+00:00",
    "season": 2024,
    "home": "Cagliari",
    "away": "Lazio",
    "home_id": 490,
    "away_id": 487,
    "home_score": 1,
    "away_score": 2,
    "points": 0,
    "is_home": true,
    "corners_for": 0,
    "corners_ag": 0
  },
  {
    "date": "2025-02-09T14:00:00+00:00",
    "season": 2024,
    "home": "Cagliari",
    "away": "Parma",
    "home_id": 490,
    "away_id": 523,
    "home_score": 2,
    "away_score": 1,
    "points": 3,
    "is_home": true,
    "corners_for": 0,
    "corners_ag": 0
  },
  {
    "date": "2025-02-15T14:00:00+00:00",
    "season": 2024,
    "home": "Atalanta",
    "away": "Cagliari",
    "home_id": 499,
    "away_id": 490,
    "home_score": 0,
    "away_score": 0,
    "points": 1,
    "is_home": false,
    "corners_for": 0,
    "corners_ag": 0
  },
  {
    "date": "2025-02-23T19:45:00+00:00",
    "season": 2024,
    "home": "Cagliari",
    "away": "Juventus",
    "home_id": 490,
    "away_id": 496,
    "home_score": 0,
    "away_score": 1,
    "points": 0,
    "is_home": true,
    "corners_for": 0,
    "corners_ag": 0
  },
  {
    "date": "2025-03-02T14:00:00+00:00",
    "season": 2024,
    "home": "Bologna",
    "away": "Cagliari",
    "home_id": 500,
    "away_id": 490,
    "home_score": 2,
    "away_score": 1,
    "points": 0,
    "is_home": false,
    "corners_for": 0,
    "corners_ag": 0
  },
  {
    "date": "2025-03-07T19:45:00+00:00",
    "season": 2024,
    "home": "Cagliari",
    "away": "Genoa",
    "home_id": 490,
    "away_id": 495,
    "home_score": 1,
    "away_score": 1,
    "points": 1,
    "is_home": true,
    "corners_for": 0,
    "corners_ag": 0
  },
  {
    "date": "2025-03-16T15:00:00+00:00",
    "season": 2024,
    "home": "AS Roma",
    "away": "Cagliari",
    "home_id": 497,
    "away_id": 490,
    "home_score": 1,
    "away_score": 0,
    "points": 0,
    "is_home": false,
    "corners_for": 0,
    "corners_ag": 0
  },
  {
    "date": "2025-03-30T10:30:00+00:00",
    "season": 2024,
    "home": "Cagliari",
    "away": "Monza",
    "home_id": 490,
    "away_id": 1579,
    "home_score": 3,
    "away_score": 0,
    "points": 3,
    "is_home": true,
    "corners_for": 0,
    "corners_ag": 0
  },
  {
    "date": "2025-04-06T13:00:00+00:00",
    "season": 2024,
    "home": "Empoli",
    "away": "Cagliari",
    "home_id": 511,
    "away_id": 490,
    "home_score": 0,
    "away_score": 0,
    "points": 1,
    "is_home": false,
    "corners_for": 0,
    "corners_ag": 0
  },
  {
    "date": "2025-04-12T16:00:00+00:00",
    "season": 2024,
    "home": "Inter",
    "away": "Cagliari",
    "home_id": 505,
    "away_id": 490,
    "home_score": 3,
    "away_score": 1,
    "points": 0,
    "is_home": false,
    "corners_for": 0,
    "corners_ag": 0
  },
  {
    "date": "2025-04-23T16:30:00+00:00",
    "season": 2024,
    "home": "Cagliari",
    "away": "Fiorentina",
    "home_id": 490,
    "away_id": 502,
    "home_score": 1,
    "away_score": 2,
    "points": 0,
    "is_home": true,
    "corners_for": 0,
    "corners_ag": 0
  },
  {
    "date": "2025-04-28T18:45:00+00:00",
    "season": 2024,
    "home": "Hellas Verona",
    "away": "Cagliari",
    "home_id": 504,
    "away_id": 490,
    "home_score": 0,
    "away_score": 2,
    "points": 3,
    "is_home": false,
    "corners_for": 0,
    "corners_ag": 0
  },
  {
    "date": "2025-05-03T13:00:00+00:00",
    "season": 2024,
    "home": "Cagliari",
    "away": "Udinese",
    "home_id": 490,
    "away_id": 494,
    "home_score": 1,
    "away_score": 2,
    "points": 0,
    "is_home": true,
    "corners_for": 0,
    "corners_ag": 0
  },
  {
    "date": "2025-05-10T13:00:00+00:00",
    "season": 2024,
    "home": "Como",
    "away": "Cagliari",
    "home_id": 895,
    "away_id": 490,
    "home_score": 3,
    "away_score": 1,
    "points": 0,
    "is_home": false,
    "corners_for": 0,
    "corners_ag": 0
  },
  {
    "date": "2025-05-18T18:45:00+00:00",
    "season": 2024,
    "home": "Cagliari",
    "away": "Venezia",
    "home_id": 490,
    "away_id": 517,
    "home_score": 3,
    "away_score": 0,
    "points": 3,
    "is_home": true,
    "corners_for": 0,
    "corners_ag": 0
  },
  {
    "date": "2025-05-23T18:45:00+00:00",
    "season": 2024,
    "home": "Napoli",
    "away": "Cagliari",
    "home_id": 492,
    "away_id": 490,
    "home_score": 2,
    "away_score": 0,
    "points": 0,
    "is_home": false,
    "corners_for": 0,
    "corners_ag": 0
  },
  {
    "date": "2024-07-25T15:00:00+00:00",
    "season": 2024,
    "home": "Cagliari",
    "away": "Como",
    "home_id": 490,
    "away_id": 895,
    "home_score": 1,
    "away_score": 3,
    "points": 0,
    "is_home": true,
    "corners_for": 0,
    "corners_ag": 0
  },
  {
    "date": "2024-07-30T17:00:00+00:00",
    "season": 2024,
    "home": "Cagliari",
    "away": "Catanzaro",
    "home_id": 490,
    "away_id": 1687,
    "home_score": 2,
    "away_score": 0,
    "points": 3,
    "is_home": true,
    "corners_for": 0,
    "corners_ag": 0
  },
  {
    "date": "2024-08-03T15:00:00+00:00",
    "season": 2024,
    "home": "Modena",
    "away": "Cagliari",
    "home_id": 899,
    "away_id": 490,
    "home_score": 2,
    "away_score": 2,
    "points": 1,
    "is_home": false,
    "corners_for": 0,
    "corners_ag": 0
  },
  {
    "date": "2024-08-12T19:15:00+00:00",
    "season": 2024,
    "home": "Cagliari",
    "away": "Carrarese",
    "home_id": 490,
    "away_id": 1581,
    "home_score": 3,
    "away_score": 1,
    "points": 3,
    "is_home": true,
    "corners_for": 0,
    "corners_ag": 0
  },
  {
    "date": "2024-09-24T16:30:00+00:00",
    "season": 2024,
    "home": "Cagliari",
    "away": "Cremonese",
    "home_id": 490,
    "away_id": 520,
    "home_score": 1,
    "away_score": 0,
    "points": 3,
    "is_home": true,
    "corners_for": 0,
    "corners_ag": 0
  },
  {
    "date": "2024-12-17T20:00:00+00:00",
    "season": 2024,
    "home": "Juventus",
    "away": "Cagliari",
    "home_id": 496,
    "away_id": 490,
    "home_score": 4,
    "away_score": 0,
    "points": 0,
    "is_home": false,
    "corners_for": 0,
    "corners_ag": 0
  }
]