[
  {
    "date": "2024-08-10T11:30:00+00:00",
    "season": 2024,
    "home": "Hull City",
    "away": "Bristol City",
    "home_id": 64,
    "away_id": 56,
    "home_score": 1,
    "away_score": 1,
    "points": 1,
    "is_home": false,
    "corners_for": 0,
    "corners_ag": 0
  },
  {
    "date": "2024-08-17T14:00:00+00:00",
    "season": 2024,
    "home": "Bristol City",
    "away": "Millwall",
    "home_id": 56,
    "away_id": 58,
    "home_score": 4,
    "away_score": 3,
    "points": 3,
    "is_home": true,
    "corners_for": 0,
    "corners_ag": 0
  },
  {
    "date": "2024-08-24T11:30:00+00:00",
    "season": 2024,
    "home": "Bristol City",
    "away": "Coventry",
    "home_id": 56,
    "away_id": 1346,
    "home_score": 1,
    "away_score": 1,
    "points": 1,
    "is_home": true,
    "corners_for": 0,
    "corners_ag": 0
  },
  {
    "date": "2024-08-31T14:00:00+00:00",
    "season": 2024,
    "home": "Derby",
    "away": "Bristol City",
    "home_id": 69,
    "away_id": 56,
    "home_score": 3,
    "away_score": 0,
    "points": 0,
    "is_home": false,
    "corners_for": 0,
    "corners_ag": 0
  },
  {
    "date": "2024-09-14T14:00:00+00:00",
    "season": 2024,
    "home": "Blackburn",
    "away": "Bristol City",
    "home_id": 67,
    "away_id": 56,
    "home_score": 3,
    "away_score": 0,
    "points": 0,
    "is_home": false,
    "corners_for": 0,
    "corners_ag": 0
  },
  {
    "date": "2024-09-21T14:00:00+00:00",
    "season": 2024,
    "home": "Bristol City",
    "away": "Oxford United",
    "home_id": 56,
    "away_id": 1338,
    "home_score": 2,
    "away_score": 1,
    "points": 3,
    "is_home": true,
    "corners_for": 0,
    "corners_ag": 0
  },
  {
    "date": "2024-09-29T14:00:00+00:00",
    "season": 2024,
    "home": "Swansea",
    "away": "Bristol City",
    "home_id": 76,
    "away_id": 56,
    "home_score": 1,
    "away_score": 1,
    "points": 1,
    "is_home": false,
    "corners_for": 0,
    "corners_ag": 0
  },
  {
    "date": "2024-10-02T19:00:00+00:00",
    "season": 2024,
    "home": "Bristol City",
    "away": "Sheffield Wednesday",
    "home_id": 56,
    "away_id": 74,
    "home_score": 0,
    "away_score": 0,
    "points": 1,
    "is_home": true,
    "corners_for": 0,
    "corners_ag": 0
  },
  {
    "date": "2024-10-06T14:00:00+00:00",
    "season": 2024,
    "home": "Bristol City",
    "away": "Cardiff",
    "home_id": 56,
    "away_id": 43,
    "home_score": 1,
    "away_score": 1,
    "points": 1,
    "is_home": true,
    "corners_for": 0,
    "corners_ag": 0
  },
  {
    "date": "2024-10-19T14:00:00+00:00",
    "season": 2024,
    "home": "Middlesbrough",
    "away": "Bristol City",
    "home_id": 70,
    "away_id": 56,
    "home_score": 0,
    "away_score": 2,
    "points": 3,
    "is_home": false,
    "corners_for": 0,
    "corners_ag": 0
  },
  {
    "date": "2024-10-22T18:45:00+00:00",
    "season": 2024,
    "home": "Stoke City",
    "away": "Bristol City",
    "home_id": 75,
    "away_id": 56,
    "home_score": 2,
    "away_score": 2,
    "points": 1,
    "is_home": false,
    "corners_for": 0,
    "corners_ag": 0
  },
  {
    "date": "2024-10-26T11:30:00+00:00",
    "season": 2024,
    "home": "Bristol City",
    "away": "Leeds",
    "home_id": 56,
    "away_id": 63,
    "home_score": 0,
    "away_score": 0,
    "points": 1,
    "is_home": true,
    "corners_for": 0,
    "corners_ag": 0
  },
  {
    "date": "2024-11-02T15:00:00+00:00",
    "season": 2024,
    "home": "Preston",
    "away": "Bristol City",
    "home_id": 59,
    "away_id": 56,
    "home_score": 1,
    "away_score": 3,
    "points": 3,
    "is_home": false,
    "corners_for": 0,
    "corners_ag": 0
  },
  {
    "date": "2024-11-05T19:45:00+00:00",
    "season": 2024,
    "home": "Bristol City",
    "away": "Sheffield Utd",
    "home_id": 56,
    "away_id": 62,
    "home_score": 1,
    "away_score": 2,
    "points": 0,
    "is_home": true,
    "corners_for": 0,
    "corners_ag": 0
  },
  {
    "date": "2024-11-09T15:00:00+00:00",
    "season": 2024,
    "home": "Norwich",
    "away": "Bristol City",
    "home_id": 71,
    "away_id": 56,
    "home_score": 0,
    "away_score": 2,
    "points": 3,
    "is_home": false,
    "corners_for": 0,
    "corners_ag": 0
  },
  {
    "date": "2024-11-23T12:30:00+00:00",
    "season": 2024,
    "home": "Bristol City",
    "away": "Burnley",
    "home_id": 56,
    "away_id": 44,
    "home_score": 0,
    "away_score": 1,
    "points": 0,
    "is_home": true,
    "corners_for": 0,
    "corners_ag": 0
  },
  {
    "date": "2024-11-26T19:45:00+00:00",
    "season": 2024,
    "home": "Watford",
    "away": "Bristol City",
    "home_id": 38,
    "away_id": 56,
    "home_score": 1,
    "away_score": 0,
    "points": 0,
    "is_home": false,
    "corners_for": 0,
    "corners_ag": 0
  },
  {
    "date": "2024-11-30T15:00:00+00:00",
    "season": 2024,
    "home": "Bristol City",
    "away": "Plymouth",
    "home_id": 56,
    "away_id": 1357,
    "home_score": 4,
    "away_score": 0,
    "points": 3,
    "is_home": true,
    "corners_for": 0,
    "corners_ag": 0
  },
  {
    "date": "2024-12-07T15:00:00+00:00",
    "season": 2024,
    "home": "Portsmouth",
    "away": "Bristol City",
    "home_id": 1355,
    "away_id": 56,
    "home_score": 3,
    "away_score": 0,
    "points": 0,
    "is_home": false,
    "corners_for": 0,
    "corners_ag": 0
  },
  {
    "date": "2024-12-10T19:45:00+00:00",
    "season": 2024,
    "home": "Sunderland",
    "away": "Bristol City",
    "home_id": 746,
    "away_id": 56,
    "home_score": 1,
    "away_score": 1,
    "points": 1,
    "is_home": false,
    "corners_for": 0,
    "corners_ag": 0
  },
  {
    "date": "2024-12-14T12:30:00+00:00",
    "season": 2024,
    "home": "Bristol City",
    "away": "QPR",
    "home_id": 56,
    "away_id": 72,
    "home_score": 1,
    "away_score": 1,
    "points": 1,
    "is_home": true,
    "corners_for": 0,
    "corners_ag": 0
  },
  {
    "date": "2024-12-22T15:00:00+00:00",
    "season": 2024,
    "home": "West Brom",
    "away": "Bristol City",
    "home_id": 60,
    "away_id": 56,
    "home_score": 2,
    "away_score": 0,
    "points": 0,
    "is_home": false,
    "corners_for": 0,
    "corners_ag": 0
  },
  {
    "date": "2024-12-26T15:00:00+00:00",
    "season": 2024,
    "home": "Bristol City",
    "away": "Luton",
    "home_id": 56,
    "away_id": 1359,
    "home_score": 1,
    "away_score": 0,
    "points": 3,
    "is_home": true,
    "corners_for": 0,
    "corners_ag": 0
  },
  {
    "date": "2024-12-29T15:00:00+00:00",
    "season": 2024,
    "home": "Bristol City",
    "away": "Portsmouth",
    "home_id": 56,
    "away_id": 1355,
    "home_score": 3,
    "away_score": 0,
    "points": 3,
    "is_home": true,
    "corners_for": 0,
    "corners_ag": 0
  },
  {
    "date": "2025-01-01T12:30:00+00:00",
    "season": 2024,
    "home": "Plymouth",
    "away": "Bristol City",
    "home_id": 1357,
    "away_id": 56,
    "home_score": 2,
    "away_score": 2,
    "points": 1,
    "is_home": false,
    "corners_for": 0,
    "corners_ag": 0
  },
  {
    "date": "2025-01-04T15:00:00+00:00",
    "season": 2024,
    "home": "Bristol City",
    "away": "Derby",
    "home_id": 56,
    "away_id": 69,
    "home_score": 1,
    "away_score": 0,
    "points": 3,
    "is_home": true,
    "corners_for": 0,
    "corners_ag": 0
  },
  {
    "date": "2025-01-18T15:00:00+00:00",
    "season": 2024,
    "home": "Coventry",
    "away": "Bristol City",
    "home_id": 1346,
    "away_id": 56,
    "home_score": 1,
    "away_score": 0,
    "points": 0,
    "is_home": false,
    "corners_for": 0,
    "corners_ag": 0
  },
  {
    "date": "2025-01-22T19:45:00+00:00",
    "season": 2024,
    "home": "Sheffield Wednesday",
    "away": "Bristol City",
    "home_id": 74,
    "away_id": 56,
    "home_score": 2,
    "away_score": 2,
    "points": 1,
    "is_home": false,
    "corners_for": 0,
    "corners_ag": 0
  },
  {
    "date": "2025-01-25T15:00:00+00:00",
    "season": 2024,
    "home": "Bristol City",
    "away": "Blackburn",
    "home_id": 56,
    "away_id": 67,
    "home_score": 2,
    "away_score": 1,
    "points": 3,
    "is_home": true,
    "corners_for": 0,
    "corners_ag": 0
  },
  {
    "date": "2025-02-01T12:30:00+00:00",
    "season": 2024,
    "home": "Oxford United",
    "away": "Bristol City",
    "home_id": 1338,
    "away_id": 56,
    "home_score": 1,
    "away_score": 1,
    "points": 1,
    "is_home": false,
    "corners_for": 0,
    "corners_ag": 0
  },
  {
    "date": "2025-02-09T12:00:00+00:00",
    "season": 2024,
    "home": "Bristol City",
    "away": "Swansea",
    "home_id": 56,
    "away_id": 76,
    "home_score": 0,
    "away_score": 1,
    "points": 0,
    "is_home": true,
    "corners_for": 0,
    "corners_ag": 0
  },
  {
    "date": "2025-02-12T19:45:00+00:00",
    "season": 2024,
    "home": "Bristol City",
    "away": "Stoke City",
    "home_id": 56,
    "away_id": 75,
    "home_score": 2,
    "away_score": 0,
    "points": 3,
    "is_home": true,
    "corners_for": 0,
    "corners_ag": 0
  },
  {
    "date": "2025-02-15T12:30:00+00:00",
    "season": 2024,
    "home": "Cardiff",
    "away": "Bristol City",
    "home_id": 43,
    "away_id": 56,
    "home_score": 1,
    "away_score": 1,
    "points": 1,
    "is_home": false,
    "corners_for": 0,
    "corners_ag": 0
  },
  {
    "date": "2025-02-21T19:45:00+00:00",
    "season": 2024,
    "home": "Bristol City",
    "away": "Middlesbrough",
    "home_id": 56,
    "away_id": 70,
    "home_score": 2,
    "away_score": 1,
    "points": 3,
    "is_home": true,
    "corners_for": 0,
    "corners_ag": 0
  },
  {
    "date": "2025-03-04T19:45:00+00:00",
    "season": 2024,
    "home": "Millwall",
    "away": "Bristol City",
    "home_id": 58,
    "away_id": 56,
    "home_score": 0,
    "away_score": 2,
    "points": 3,
    "is_home": false,
    "corners_for": 0,
    "corners_ag": 0
  },
  {
    "date": "2025-03-08T15:00:00+00:00",
    "season": 2024,
    "home": "Bristol City",
    "away": "Hull City",
    "home_id": 56,
    "away_id": 64,
    "home_score": 1,
    "away_score": 1,
    "points": 1,
    "is_home": true,
    "corners_for": 0,
    "corners_ag": 0
  },
  {
    "date": "2025-03-11T20:00:00+00:00",
    "season": 2024,
    "home": "Sheffield Utd",
    "away": "Bristol City",
    "home_id": 62,
    "away_id": 56,
    "home_score": 1,
    "away_score": 1,
    "points": 1,
    "is_home": false,
    "corners_for": 0,
    "corners_ag": 0
  },
  {
    "date": "2025-03-14T20:00:00+00:00",
    "season": 2024,
    "home": "Bristol City",
    "away": "Norwich",
    "home_id": 56,
    "away_id": 71,
    "home_score": 2,
    "away_score": 1,
    "points": 3,
    "is_home": true,
    "corners_for": 0,
    "corners_ag": 0
  },
  {
    "date": "2025-03-29T15:00:00+00:00",
    "season": 2024,
    "home": "Burnley",
    "away": "Bristol City",
    "home_id": 44,
    "away_id": 56,
    "home_score": 1,
    "away_score": 0,
    "points": 0,
    "is_home": false,
    "corners_for": 0,
    "corners_ag": 0
  },
  {
    "date": "2025-04-05T14:00:00+00:00",
    "season": 2024,
    "home": "Bristol City",
    "away": "Watford",
    "home_id": 56,
    "away_id": 38,
    "home_score": 2,
    "away_score": 1,
    "points": 3,
    "is_home": true,
    "corners_for": 0,
    "corners_ag": 0
  },
  {
    "date": "2025-04-08T18:45:00+00:00",
    "season": 2024,
    "home": "Bristol City",
    "away": "West Brom",
    "home_id": 56,
    "away_id": 60,
    "home_score": 2,
    "away_score": 1,
    "points": 3,
    "is_home": true,
    "corners_for": 0,
    "corners_ag": 0
  },
  {
    "date": "2025-04-12T14:00:00+00:00",
    "season": 2024,
    "home": "QPR",
    "away": "Bristol City",
    "home_id": 72,
    "away_id": 56,
    "home_score": 1,
    "away_score": 1,
    "points": 1,
    "is_home": false,
    "corners_for": 0,
    "corners_ag": 0
  },
  {
    "date": "2025-04-18T14:00:00+00:00",
    "season": 2024,
    "home": "Bristol City",
    "away": "Sunderland",
    "home_id": 56,
    "away_id": 746,
    "home_score": 2,
    "away_score": 1,
    "points": 3,
    "is_home": true,
    "corners_for": 0,
    "corners_ag": 0
  },
  {
    "date": "2025-04-21T14:00:00+00:00",
    "season": 2024,
    "home": "Luton",
    "away": "Bristol City",
    "home_id": 1359,
    "away_id": 56,
    "home_score": 3,
    "away_score": 1,
    "points": 0,
    "is_home": false,
    "corners_for": 0,
    "corners_ag": 0
  },
  {
    "date": "2025-04-28T19:00:00+00:00",
    "season": 2024,
    "home": "Leeds",
    "away": "Bristol City",
    "home_id": 63,
    "away_id": 56,
    "home_score": 4,
    "away_score": 0,
    "points": 0,
    "is_home": false,
    "corners_for": 0,
    "corners_ag": 0
  },
  {
    "date": "2025-05-03T11:30:00+00:00",
    "season": 2024,
    "home": "Bristol City",
    "away": "Preston",
    "home_id": 56,
    "away_id": 59,
    "home_score": 2,
    "away_score": 2,
    "points": 1,
    "is_home": true,
    "corners_for": 0,
    "corners_ag": 0
  },
  {
    "date": "2024-07-23T11:00:00+00:00",
    "season": 2024,
    "home": "Bristol City",
    "away": "Newport County",
    "home_id": 56,
    "away_id": 1367,
    "home_score": 2,
    "away_score": 0,
    "points": 3,
    "is_home": true,
    "corners_for": 0,
    "corners_ag": 0
  },
  {
    "date": "2024-07-23T18:45:00+00:00",
    "season": 2024,
    "home": "Aldershot Town",
    "away": "Bristol City",
    "home_id": 1818,
    "away_id": 56,
    "home_score": 0,
    "away_score": 2,
    "points": 3,
    "is_home": false,
    "corners_for": 0,
    "corners_ag": 0
  },
  {
    "date": "2024-07-26T18:45:00+00:00",
    "season": 2024,
    "home": "Cheltenham",
    "away": "Bristol City",
    "home_id": 1372,
    "away_id": 56,
    "home_score": 0,
    "away_score": 3,
    "points": 3,
    "is_home": false,
    "corners_for": 0,
    "corners_ag": 0
  },
  {
    "date": "2024-07-27T12:00:00+00:00",
    "season": 2024,
    "home": "Bristol City",
    "away": "Exeter City",
    "home_id": 56,
    "away_id": 1364,
    "home_score": 2,
    "away_score": 1,
    "points": 3,
    "is_home": true,
    "corners_for": 0,
    "corners_ag": 0
  },
  {
    "date": "2024-08-13T18:45:00+00:00",
    "season": 2024,
    "home": "Bristol City",
    "away": "Coventry",
    "home_id": 56,
    "away_id": 1346,
    "home_score": 0,
    "away_score": 1,
    "points": 0,
    "is_home": true,
    "corners_for": 0,
    "corners_ag": 0
  },
  {
    "date": "2024-08-03T14:00:00+00:00",
    "season": 2024,
    "home": "Bristol City",
    "away": "Willem II",
    "home_id": 56,
    "away_id": 195,
    "home_score": 0,
    "away_score": 0,
    "points": 1,
    "is_home": true,
    "corners_for": 0,
    "corners_ag": 0
  },
  {
    "date": "2025-01-11T12:00:00+00:00",
    "season": 2024,
    "home": "Bristol City",
    "away": "Wolves",
    "home_id": 56,
    "away_id": 39,
    "home_score": 1,
    "away_score": 2,
    "points": 0,
    "is_home": true,
    "corners_for": 0,
    "corners_ag": 0
  },
  {
    "date": "2025-05-08T19:00:00+00:00",
    "season": 2024,
    "home": "Bristol City",
    "away": "Sheffield Utd",
    "home_id": 56,
    "away_id": 62,
    "home_score": 0,
    "away_score": 3,
    "points": 0,
    "is_home": true,
    "corners_for": 0,
    "corners_ag": 0
  },
  {
    "date": "2025-05-12T19:00:00+00:00",
    "season": 2024,
    "home": "Sheffield Utd",
    "away": "Bristol City",
    "home_id": 62,
    "away_id": 56,
    "home_score": 3,
    "away_score": 0,
    "points": 0,
    "is_home": false,
    "corners_for": 0,
    "corners_ag": 0
  }
]