[
  {
    "position": 1,
    "team_id": 157,
    "team": "Bayern Munich",
    "points": 71,
    "won": 21,
    "draw": 8,
    "lost": 5,
    "gf": 92,
    "ga": 38,
    "gd": 54,
    "form": "WLWWW"
  },
  {
    "position": 2,
    "team_id": 165,
    "team": "Borussia Dortmund",
    "points": 71,
    "won": 22,
    "draw": 5,
    "lost": 7,
    "gf": 83,
    "ga": 44,
    "gd": 39,
    "form": "DWWWD"
  },
  {
    "position": 3,
    "team_id": 173,
    "team": "RB Leipzig",
    "points": 66,
    "won": 20,
    "draw": 6,
    "lost": 8,
    "gf": 64,
    "ga": 41,
    "gd": 23,
    "form": "WWWWW"
  },
  {
    "position": 4,
    "team_id": 182,
    "team": "Union Berlin",
    "points": 62,
    "won": 18,
    "draw": 8,
    "lost": 8,
    "gf": 51,
    "ga": 38,
    "gd": 13,
    "form": "WLWLD"
  },
  {
    "position": 5,
    "team_id": 160,
    "team": "SC Freiburg",
    "points": 59,
    "won": 17,
    "draw": 8,
    "lost": 9,
    "gf": 51,
    "ga": 44,
    "gd": 7,
    "form": "LWLLW"
  },
  {
    "position": 6,
    "team_id": 168,
    "team": "Bayer Leverkusen",
    "points": 50,
    "won": 14,
    "draw": 8,
    "lost": 12,
    "gf": 57,
    "ga": 49,
    "gd": 8,
    "form": "LDDLD"
  },
  {
    "position": 7,
    "team_id": 169,
    "team": "Eintracht Frankfurt",
    "points": 50,
    "won": 13,
    "draw": 11,
    "lost": 10,
    "gf": 58,
    "ga": 52,
    "gd": 6,
    "form": "WDWLD"
  },
  {
    "position": 8,
    "team_id": 161,
    "team": "VfL Wolfsburg",
    "points": 49,
    "won": 13,
    "draw": 10,
    "lost": 11,
    "gf": 57,
    "ga": 48,
    "gd": 9,
    "form": "LLWLW"
  },
  {
    "position": 9,
    "team_id": 164,
    "team": "FSV Mainz 05",
    "points": 46,
    "won": 12,
    "draw": 10,
    "lost": 12,
    "gf": 54,
    "ga": 55,
    "gd": -1,
    "form": "DLLLL"
  },
  {
    "position": 10,
    "team_id": 163,
    "team": "Borussia Monchengladbach",
    "points": 43,
    "won": 11,
    "draw": 10,
    "lost": 13,
    "gf": 52,
    "ga": 55,
    "gd": -3,
    "form": "WDLWL"
  },
  {
    "position": 11,
    "team_id": 192,
    "team": "FC Koln",
    "points": 42,
    "won": 10,
    "draw": 12,
    "lost": 12,
    "gf": 49,
    "ga": 54,
    "gd": -5,
    "form": "LDWWL"
  },
  {
    "position": 12,
    "team_id": 167,
    "team": "1899 Hoffenheim",
    "points": 36,
    "won": 10,
    "draw": 6,
    "lost": 18,
    "gf": 48,
    "ga": 57,
    "gd": -9,
    "form": "DWLWL"
  },
  {
    "position": 13,
    "team_id": 162,
    "team": "Werder Bremen",
    "points": 36,
    "won": 10,
    "draw": 6,
    "lost": 18,
    "gf": 51,
    "ga": 64,
    "gd": -13,
    "form": "LDLLL"
  },
  {
    "position": 14,
    "team_id": 176,
    "team": "VfL BOCHUM",
    "points": 35,
    "won": 10,
    "draw": 5,
    "lost": 19,
    "gf": 40,
    "ga": 72,
    "gd": -32,
    "form": "WDWLD"
  },
  {
    "position": 15,
    "team_id": 170,
    "team": "FC Augsburg",
    "points": 34,
    "won": 9,
    "draw": 7,
    "lost": 18,
    "gf": 42,
    "ga": 63,
    "gd": -21,
    "form": "LLLWD"
  },
  {
    "position": 16,
    "team_id": 172,
    "team": "VfB Stuttgart",
    "points": 33,
    "won": 7,
    "draw": 12,
    "lost": 15,
    "gf": 45,
    "ga": 57,
    "gd": -12,
    "form": "DWDLW"
  },
  {
    "position": 17,
    "team_id": 174,
    "team": "FC Schalke 04",
    "points": 31,
    "won": 7,
    "draw": 10,
    "lost": 17,
    "gf": 35,
    "ga": 71,
    "gd": -36,
    "form": "LDLWW"
  },
  {
    "position": 18,
    "team_id": 159,
    "team": "Hertha Berlin",
    "points": 29,
    "won": 7,
    "draw": 8,
    "lost": 19,
    "gf": 42,
    "ga": 69,
    "gd": -27,
    "form": "WDLWL"
  }
]